[{"heart_rate":54.0,"heart_rate_max":58.0,"heart_rate_min":51.0,"start_time":1764287940000,"end_time":1764287999000},{"heart_rate":54.0,"heart_rate_max":56.0,"heart_rate_min":52.0,"start_time":1764287880000,"end_time":1764287939000},{"heart_rate":57.0,"heart_rate_max":72.0,"heart_rate_min":51.0,"start_time":1764287820000,"end_time":1764287879000},{"heart_rate":55.0,"heart_rate_max":65.0,"heart_rate_min":52.0,"start_time":1764287760000,"end_time":1764287819000},{"heart_rate":61.0,"heart_rate_max":66.0,"heart_rate_min":53.0,"start_time":1764287700000,"end_time":1764287759000},{"heart_rate":78.0,"heart_rate_max":80.0,"heart_rate_min":78.0,"start_time":1764287640000,"end_time":1764287699000},{"heart_rate":73.0,"heart_rate_max":87.0,"heart_rate_min":61.0,"start_time":1764287580000,"end_time":1764287639000},{"heart_rate":80.0,"heart_rate_max":82.0,"heart_rate_min":79.0,"start_time":1764287520000,"end_time":1764287579000},{"heart_rate":79.0,"heart_rate_max":83.0,"heart_rate_min":78.0,"start_time":1764287460000,"end_time":1764287519000},{"heart_rate":77.0,"heart_rate_max":85.0,"heart_rate_min":62.0,"start_time":1764287400000,"end_time":1764287459000},{"heart_rate":84.0,"heart_rate_max":85.0,"heart_rate_min":84.0,"start_time":1764286020000,"end_time":1764286079000},{"heart_rate":75.0,"heart_rate_max":79.0,"heart_rate_min":72.0,"start_time":1764285900000,"end_time":1764285959000},{"heart_rate":77.0,"heart_rate_max":78.0,"heart_rate_min":77.0,"start_time":1764285840000,"end_time":1764285899000},{"heart_rate":62.0,"heart_rate_max":75.0,"heart_rate_min":58.0,"start_time":1764285780000,"end_time":1764285839000},{"heart_rate":61.0,"heart_rate_max":64.0,"heart_rate_min":56.0,"start_time":1764285720000,"end_time":1764285779000},{"heart_rate":61.0,"heart_rate_max":65.0,"heart_rate_min":55.0,"start_time":1764285660000,"end_time":1764285719000},{"heart_rate":65.0,"heart_rate_max":73.0,"heart_rate_min":61.0,"start_time":1764285600000,"end_time":1764285659000},{"heart_rate":61.0,"heart_rate_max":67.0,"heart_rate_min":58.0,"start_time":1764285540000,"end_time":1764285599000},{"heart_rate":61.0,"heart_rate_max":68.0,"heart_rate_min":54.0,"start_time":1764285480000,"end_time":1764285539000},{"heart_rate":63.0,"heart_rate_max":72.0,"heart_rate_min":57.0,"start_time":1764285420000,"end_time":1764285479000},{"heart_rate":64.0,"heart_rate_max":68.0,"heart_rate_min":61.0,"start_time":1764285360000,"end_time":1764285419000},{"heart_rate":66.0,"heart_rate_max":71.0,"heart_rate_min":61.0,"start_time":1764285300000,"end_time":1764285359000},{"heart_rate":66.0,"heart_rate_max":78.0,"heart_rate_min":59.0,"start_time":1764285240000,"end_time":1764285299000},{"heart_rate":80.0,"heart_rate_max":83.0,"heart_rate_min":79.0,"start_time":1764285180000,"end_time":1764285239000},{"heart_rate":74.0,"heart_rate_max":78.0,"heart_rate_min":67.0,"start_time":1764285120000,"end_time":1764285179000},{"heart_rate":64.0,"heart_rate_max":70.0,"heart_rate_min":62.0,"start_time":1764285060000,"end_time":1764285119000},{"heart_rate":68.0,"heart_rate_max":72.0,"heart_rate_min":64.0,"start_time":1764285000000,"end_time":1764285059000},{"heart_rate":69.0,"heart_rate_max":82.0,"heart_rate_min":68.0,"start_time":1764284940000,"end_time":1764284999000},{"heart_rate":85.0,"heart_rate_max":88.0,"heart_rate_min":80.0,"start_time":1764284880000,"end_time":1764284939000},{"heart_rate":92.0,"heart_rate_max":99.0,"heart_rate_min":88.0,"start_time":1764284820000,"end_time":1764284879000},{"heart_rate":93.0,"heart_rate_max":95.0,"heart_rate_min":91.0,"start_time":1764284760000,"end_time":1764284819000},{"heart_rate":91.0,"heart_rate_max":93.0,"heart_rate_min":89.0,"start_time":1764284700000,"end_time":1764284759000},{"heart_rate":84.0,"heart_rate_max":88.0,"heart_rate_min":80.0,"start_time":1764284640000,"end_time":1764284699000},{"heart_rate":89.0,"heart_rate_max":91.0,"heart_rate_min":87.0,"start_time":1764284580000,"end_time":1764284639000},{"heart_rate":80.0,"heart_rate_max":90.0,"heart_rate_min":74.0,"start_time":1764284520000,"end_time":1764284579000},{"heart_rate":72.0,"heart_rate_max":78.0,"heart_rate_min":69.0,"start_time":1764284460000,"end_time":1764284519000},{"heart_rate":93.0,"heart_rate_max":102.0,"heart_rate_min":76.0,"start_time":1764284400000,"end_time":1764284459000}]