[{"score":0,"score_max":2,"score_min":0,"flag":1,"level":1,"start_time":1696247820000,"end_time":1696247879000},{"score":4,"score_max":6,"score_min":4,"flag":1,"level":1,"start_time":1696247760000,"end_time":1696247819000},{"score":2,"score_max":4,"score_min":0,"flag":1,"level":1,"start_time":1696247700000,"end_time":1696247759000},{"score":0,"score_max":0,"score_min":0,"flag":1,"level":1,"start_time":1696247640000,"end_time":1696247699000},{"score":0,"score_max":0,"score_min":0,"flag":1,"level":1,"start_time":1696247580000,"end_time":1696247639000},{"score":0,"score_max":0,"score_min":0,"flag":1,"level":1,"start_time":1696247520000,"end_time":1696247579000},{"score":0,"score_max":0,"score_min":0,"flag":1,"level":1,"start_time":1696247460000,"end_time":1696247519000},{"score":0,"score_max":0,"score_min":0,"flag":1,"level":1,"start_time":1696247400000,"end_time":1696247459000},{"score":0,"score_max":0,"score_min":0,"flag":1,"level":1,"start_time":1696247340000,"end_time":1696247399000},{"score":0,"score_max":0,"score_min":0,"flag":1,"level":1,"start_time":1696247280000,"end_time":1696247339000},{"score":0,"score_max":0,"score_min":0,"flag":1,"level":1,"start_time":1696247220000,"end_time":1696247279000},{"score":0,"score_max":0,"score_min":0,"flag":1,"level":1,"start_time":1696247160000,"end_time":1696247219000},{"score":0,"score_max":0,"score_min":0,"flag":1,"level":1,"start_time":1696247100000,"end_time":1696247159000},{"score":2,"score_max":8,"score_min":0,"flag":1,"level":1,"start_time":1696247040000,"end_time":1696247099000},{"score":1,"score_max":6,"score_min":0,"flag":1,"level":1,"start_time":1696246320000,"end_time":1696246379000},{"score":60,"score_max":66,"score_min":54,"flag":1,"level":1,"start_time":1696246260000,"end_time":1696246319000},{"score":70,"score_max":81,"score_min":59,"flag":1,"level":1,"start_time":1696246200000,"end_time":1696246259000},{"score":54,"score_max":58,"score_min":49,"flag":1,"level":1,"start_time":1696246140000,"end_time":1696246199000},{"score":35,"score_max":55,"score_min":26,"flag":1,"level":1,"start_time":1696246080000,"end_time":1696246139000},{"score":63,"score_max":68,"score_min":57,"flag":1,"level":1,"start_time":1696245900000,"end_time":1696245959000},{"score":47,"score_max":53,"score_min":40,"flag":1,"level":1,"start_time":1696245840000,"end_time":1696245899000},{"score":16,"score_max":39,"score_min":5,"flag":1,"level":1,"start_time":1696245780000,"end_time":1696245839000},{"score":1,"score_max":3,"score_min":1,"flag":1,"level":1,"start_time":1696245720000,"end_time":1696245779000},{"score":1,"score_max":2,"score_min":1,"flag":1,"level":1,"start_time":1696245600000,"end_time":1696245659000}]