[{"heart_rate":57,"heart_rate_max":61,"heart_rate_min":55,"start_time":1709459940000,"end_time":1709459999000},{"heart_rate":57,"heart_rate_max":59,"heart_rate_min":57,"start_time":1709459880000,"end_time":1709459939000},{"heart_rate":58,"heart_rate_max":60,"heart_rate_min":57,"start_time":1709459820000,"end_time":1709459879000},{"heart_rate":57,"heart_rate_max":60,"heart_rate_min":55,"start_time":1709459760000,"end_time":1709459819000},{"heart_rate":58,"heart_rate_max":60,"heart_rate_min":56,"start_time":1709459700000,"end_time":1709459759000},{"heart_rate":58,"heart_rate_max":59,"heart_rate_min":57,"start_time":1709459640000,"end_time":1709459699000},{"heart_rate":56,"heart_rate_max":58,"heart_rate_min":55,"start_time":1709459580000,"end_time":1709459639000},{"heart_rate":58,"heart_rate_max":60,"heart_rate_min":57,"start_time":1709459520000,"end_time":1709459579000},{"heart_rate":57,"heart_rate_max":60,"heart_rate_min":55,"start_time":1709459460000,"end_time":1709459519000},{"heart_rate":57,"heart_rate_max":61,"heart_rate_min":54,"start_time":1709459400000,"end_time":1709459459000},{"heart_rate":56,"heart_rate_max":60,"heart_rate_min":54,"start_time":1709459340000,"end_time":1709459399000},{"heart_rate":57,"heart_rate_max":60,"heart_rate_min":55,"start_time":1709459280000,"end_time":1709459339000},{"heart_rate":60,"heart_rate_max":71,"heart_rate_min":55,"start_time":1709459220000,"end_time":1709459279000},{"heart_rate":58,"heart_rate_max":64,"heart_rate_min":54,"start_time":1709459160000,"end_time":1709459219000},{"heart_rate":57,"heart_rate_max":59,"heart_rate_min":54,"start_time":1709459100000,"end_time":1709459159000},{"heart_rate":59,"heart_rate_max":61,"heart_rate_min":58,"start_time":1709459040000,"end_time":1709459099000},{"heart_rate":56,"heart_rate_max":59,"heart_rate_min":54,"start_time":1709458980000,"end_time":1709459039000},{"heart_rate":57,"heart_rate_max":60,"heart_rate_min":55,"start_time":1709458920000,"end_time":1709458979000},{"heart_rate":57,"heart_rate_max":59,"heart_rate_min":57,"start_time":1709458860000,"end_time":1709458919000},{"heart_rate":57,"heart_rate_max":59,"heart_rate_min":55,"start_time":1709458800000,"end_time":1709458859000},{"heart_rate":57,"heart_rate_max":60,"heart_rate_min":54,"start_time":1709458740000,"end_time":1709458799000},{"heart_rate":57,"heart_rate_max":59,"heart_rate_min":56,"start_time":1709458680000,"end_time":1709458739000},{"heart_rate":57,"heart_rate_max":60,"heart_rate_min":54,"start_time":1709458620000,"end_time":1709458679000},{"heart_rate":57,"heart_rate_max":60,"heart_rate_min":55,"start_time":1709458560000,"end_time":1709458619000},{"heart_rate":56,"heart_rate_max":58,"heart_rate_min":55,"start_time":1709458500000,"end_time":1709458559000},{"heart_rate":57,"heart_rate_max":58,"heart_rate_min":56,"start_time":1709458440000,"end_time":1709458499000},{"heart_rate":57,"heart_rate_max":60,"heart_rate_min":55,"start_time":1709458380000,"end_time":1709458439000},{"heart_rate":56,"heart_rate_max":58,"heart_rate_min":55,"start_time":1709458320000,"end_time":1709458379000},{"heart_rate":55,"heart_rate_max":57,"heart_rate_min":53,"start_time":1709458260000,"end_time":1709458319000},{"heart_rate":57,"heart_rate_max":60,"heart_rate_min":55,"start_time":1709458200000,"end_time":1709458259000},{"heart_rate":55,"heart_rate_max":58,"heart_rate_min":53,"start_time":1709458140000,"end_time":1709458199000},{"heart_rate":55,"heart_rate_max":58,"heart_rate_min":53,"start_time":1709458080000,"end_time":1709458139000},{"heart_rate":58,"heart_rate_max":67,"heart_rate_min":51,"start_time":1709458020000,"end_time":1709458079000},{"heart_rate":53,"heart_rate_max":59,"heart_rate_min":52,"start_time":1709457960000,"end_time":1709458019000},{"heart_rate":54,"heart_rate_max":62,"heart_rate_min":52,"start_time":1709457900000,"end_time":1709457959000},{"heart_rate":60,"heart_rate_max":69,"heart_rate_min":56,"start_time":1709457840000,"end_time":1709457899000},{"heart_rate":57,"heart_rate_max":59,"heart_rate_min":54,"start_time":1709457780000,"end_time":1709457839000},{"heart_rate":57,"heart_rate_max":60,"heart_rate_min":56,"start_time":1709457720000,"end_time":1709457779000},{"heart_rate":58,"heart_rate_max":60,"heart_rate_min":57,"start_time":1709457660000,"end_time":1709457719000},{"heart_rate":57,"heart_rate_max":59,"heart_rate_min":55,"start_time":1709457600000,"end_time":1709457659000},{"heart_rate":56,"heart_rate_max":59,"heart_rate_min":54,"start_time":1709457540000,"end_time":1709457599000},{"heart_rate":58,"heart_rate_max":62,"heart_rate_min":55,"start_time":1709457480000,"end_time":1709457539000},{"heart_rate":54,"heart_rate_max":59,"heart_rate_min":52,"start_time":1709457420000,"end_time":1709457479000},{"heart_rate":59,"heart_rate_max":68,"heart_rate_min":54,"start_time":1709457360000,"end_time":1709457419000},{"heart_rate":55,"heart_rate_max":59,"heart_rate_min":53,"start_time":1709457300000,"end_time":1709457359000},{"heart_rate":56,"heart_rate_max":61,"heart_rate_min":53,"start_time":1709457240000,"end_time":1709457299000},{"heart_rate":54,"heart_rate_max":59,"heart_rate_min":50,"start_time":1709457180000,"end_time":1709457239000},{"heart_rate":49,"heart_rate_max":63,"heart_rate_min":46,"start_time":1709457120000,"end_time":1709457179000},{"heart_rate":57,"heart_rate_max":69,"heart_rate_min":51,"start_time":1709457060000,"end_time":1709457119000},{"heart_rate":53,"heart_rate_max":58,"heart_rate_min":51,"start_time":1709457000000,"end_time":1709457059000},{"heart_rate":58,"heart_rate_max":62,"heart_rate_min":55,"start_time":1709456940000,"end_time":1709456999000},{"heart_rate":56,"heart_rate_max":62,"heart_rate_min":56,"start_time":1709456880000,"end_time":1709456939000},{"heart_rate":60,"heart_rate_max":66,"heart_rate_min":56,"start_time":1709456820000,"end_time":1709456879000},{"heart_rate":59,"heart_rate_max":65,"heart_rate_min":54,"start_time":1709456760000,"end_time":1709456819000},{"heart_rate":53,"heart_rate_max":58,"heart_rate_min":50,"start_time":1709456700000,"end_time":1709456759000},{"heart_rate":57,"heart_rate_max":68,"heart_rate_min":49,"start_time":1709456640000,"end_time":1709456699000},{"heart_rate":52,"heart_rate_max":70,"heart_rate_min":46,"start_time":1709456580000,"end_time":1709456639000},{"heart_rate":49,"heart_rate_max":55,"heart_rate_min":46,"start_time":1709456520000,"end_time":1709456579000},{"heart_rate":54,"heart_rate_max":66,"heart_rate_min":46,"start_time":1709456460000,"end_time":1709456519000},{"heart_rate":52,"heart_rate_max":60,"heart_rate_min":48,"start_time":1709456400000,"end_time":1709456459000}]