[{"elapsed_time":1000,"interval":1,"segment":1,"source_type":4,"start_time":1759155727299},{"elapsed_time":60000,"interval":1,"segment":1,"source_type":4,"start_time":1759155786299},{"elapsed_time":120000,"interval":1,"segment":1,"source_type":4,"start_time":1759155846299},{"elapsed_time":180000,"interval":1,"segment":1,"source_type":4,"start_time":1759155906299},{"elapsed_time":240000,"interval":1,"segment":1,"source_type":4,"start_time":1759155966299},{"elapsed_time":300000,"interval":1,"segment":1,"source_type":4,"start_time":1759156026299},{"elapsed_time":360000,"interval":1,"segment":1,"source_type":4,"start_time":1759156086299},{"elapsed_time":420000,"interval":1,"segment":1,"source_type":4,"start_time":1759156146299},{"elapsed_time":480000,"interval":1,"segment":1,"source_type":4,"start_time":1759156206299},{"elapsed_time":540000,"interval":1,"segment":1,"source_type":4,"start_time":1759156266299},{"elapsed_time":600000,"interval":1,"segment":1,"source_type":4,"start_time":1759156326299},{"elapsed_time":300000,"interval":1,"segment":1,"source_type":4,"start_time":1759156026299},{"elapsed_time":660000,"interval":1,"segment":2,"source_type":4,"start_time":1759156416599},{"elapsed_time":660000,"interval":1,"segment":2,"source_type":4,"start_time":1759156416599},{"elapsed_time":718691,"interval":1,"segment":3,"source_type":4,"start_time":1759156483813},{"elapsed_time":28697,"interval":1,"segment":1,"source_type":4,"start_time":1759155754996},{"elapsed_time":29697,"interval":1,"segment":1,"source_type":4,"start_time":1759155755996},{"elapsed_time":30697,"interval":1,"segment":1,"source_type":4,"start_time":1759155756996},{"elapsed_time":74697,"interval":1,"segment":1,"source_type":4,"start_time":1759155800996},{"elapsed_time":86697,"interval":1,"segment":1,"source_type":4,"start_time":1759155812996},{"elapsed_time":87697,"interval":1,"segment":1,"source_type":4,"start_time":1759155813996},{"elapsed_time":128697,"interval":1,"segment":1,"source_type":4,"start_time":1759155854996},{"elapsed_time":131697,"interval":1,"segment":1,"source_type":4,"start_time":1759155857996},{"elapsed_time":139697,"interval":1,"segment":1,"source_type":4,"start_time":1759155865996},{"elapsed_time":140697,"interval":1,"segment":1,"source_type":4,"start_time":1759155866996},{"elapsed_time":141697,"interval":1,"segment":1,"source_type":4,"start_time":1759155867996},{"elapsed_time":142697,"interval":1,"segment":1,"source_type":4,"start_time":1759155868996},{"elapsed_time":143697,"interval":1,"segment":1,"source_type":4,"start_time":1759155869996},{"elapsed_time":144697,"interval":1,"segment":1,"source_type":4,"start_time":1759155870996},{"elapsed_time":151697,"interval":1,"segment":1,"source_type":4,"start_time":1759155877996},{"elapsed_time":152697,"interval":1,"segment":1,"source_type":4,"start_time":1759155878996},{"elapsed_time":153697,"interval":1,"segment":1,"source_type":4,"start_time":1759155879996},{"elapsed_time":154697,"interval":1,"segment":1,"source_type":4,"start_time":1759155880996},{"elapsed_time":155697,"interval":1,"segment":1,"source_type":4,"start_time":1759155881996},{"elapsed_time":156697,"interval":1,"segment":1,"source_type":4,"start_time":1759155882996},{"elapsed_time":157697,"interval":1,"segment":1,"source_type":4,"start_time":1759155883996},{"elapsed_time":158697,"interval":1,"segment":1,"source_type":4,"start_time":1759155884996},{"elapsed_time":159697,"interval":1,"segment":1,"source_type":4,"start_time":1759155885996},{"elapsed_time":160697,"interval":1,"segment":1,"source_type":4,"start_time":1759155886996},{"elapsed_time":161697,"interval":1,"segment":1,"source_type":4,"start_time":1759155887996},{"elapsed_time":162697,"interval":1,"segment":1,"source_type":4,"start_time":1759155888996},{"elapsed_time":163697,"interval":1,"segment":1,"source_type":4,"start_time":1759155889996},{"elapsed_time":164697,"interval":1,"segment":1,"source_type":4,"start_time":1759155890996},{"elapsed_time":165697,"interval":1,"segment":1,"source_type":4,"start_time":1759155891996},{"elapsed_time":166697,"interval":1,"segment":1,"source_type":4,"start_time":1759155892996},{"elapsed_time":167697,"interval":1,"segment":1,"source_type":4,"start_time":1759155893996},{"elapsed_time":168697,"interval":1,"segment":1,"source_type":4,"start_time":1759155894996},{"elapsed_time":169697,"interval":1,"segment":1,"source_type":4,"start_time":1759155895996},{"elapsed_time":170697,"interval":1,"segment":1,"source_type":4,"start_time":1759155896996},{"elapsed_time":171697,"interval":1,"segment":1,"source_type":4,"start_time":1759155897996},{"elapsed_time":172697,"interval":1,"segment":1,"source_type":4,"start_time":1759155898996},{"elapsed_time":173697,"interval":1,"segment":1,"source_type":4,"start_time":1759155899996},{"elapsed_time":174697,"interval":1,"segment":1,"source_type":4,"start_time":1759155900996},{"elapsed_time":175697,"interval":1,"segment":1,"source_type":4,"start_time":1759155901996},{"elapsed_time":176697,"interval":1,"segment":1,"source_type":4,"start_time":1759155902996},{"elapsed_time":177697,"interval":1,"segment":1,"source_type":4,"start_time":1759155903996},{"elapsed_time":178697,"interval":1,"segment":1,"source_type":4,"start_time":1759155904996},{"elapsed_time":179697,"interval":1,"segment":1,"source_type":4,"start_time":1759155905996},{"elapsed_time":180697,"interval":1,"segment":1,"source_type":4,"start_time":1759155906996},{"elapsed_time":181697,"interval":1,"segment":1,"source_type":4,"start_time":1759155907996},{"elapsed_time":182697,"interval":1,"segment":1,"source_type":4,"start_time":1759155908996},{"elapsed_time":183697,"interval":1,"segment":1,"source_type":4,"start_time":1759155909996},{"elapsed_time":184697,"interval":1,"segment":1,"source_type":4,"start_time":1759155910996},{"elapsed_time":185697,"interval":1,"segment":1,"source_type":4,"start_time":1759155911996},{"elapsed_time":186697,"interval":1,"segment":1,"source_type":4,"start_time":1759155912996},{"elapsed_time":187697,"interval":1,"segment":1,"source_type":4,"start_time":1759155913996},{"elapsed_time":188697,"interval":1,"segment":1,"source_type":4,"start_time":1759155914996},{"elapsed_time":189697,"interval":1,"segment":1,"source_type":4,"start_time":1759155915996},{"elapsed_time":190697,"interval":1,"segment":1,"source_type":4,"start_time":1759155916996},{"elapsed_time":191697,"interval":1,"segment":1,"source_type":4,"start_time":1759155917996},{"elapsed_time":192697,"interval":1,"segment":1,"source_type":4,"start_time":1759155918996},{"elapsed_time":193697,"interval":1,"segment":1,"source_type":4,"start_time":1759155919996},{"elapsed_time":194697,"interval":1,"segment":1,"source_type":4,"start_time":1759155920996},{"elapsed_time":195697,"interval":1,"segment":1,"source_type":4,"start_time":1759155921996},{"elapsed_time":196697,"interval":1,"segment":1,"source_type":4,"start_time":1759155922996},{"elapsed_time":197697,"interval":1,"segment":1,"source_type":4,"start_time":1759155923996},{"elapsed_time":198697,"interval":1,"segment":1,"source_type":4,"start_time":1759155924996},{"elapsed_time":199697,"interval":1,"segment":1,"source_type":4,"start_time":1759155925996},{"elapsed_time":200697,"interval":1,"segment":1,"source_type":4,"start_time":1759155926996},{"elapsed_time":201697,"interval":1,"segment":1,"source_type":4,"start_time":1759155927996},{"elapsed_time":202697,"interval":1,"segment":1,"source_type":4,"start_time":1759155928996},{"elapsed_time":203697,"interval":1,"segment":1,"source_type":4,"start_time":1759155929996},{"elapsed_time":204697,"interval":1,"segment":1,"source_type":4,"start_time":1759155930996},{"elapsed_time":205697,"interval":1,"segment":1,"source_type":4,"start_time":1759155931996},{"elapsed_time":206697,"interval":1,"segment":1,"source_type":4,"start_time":1759155932996},{"elapsed_time":207697,"interval":1,"segment":1,"source_type":4,"start_time":1759155933996},{"elapsed_time":208697,"interval":1,"segment":1,"source_type":4,"start_time":1759155934996},{"elapsed_time":209697,"interval":1,"segment":1,"source_type":4,"start_time":1759155935996},{"elapsed_time":210697,"interval":1,"segment":1,"source_type":4,"start_time":1759155936996},{"elapsed_time":211697,"interval":1,"segment":1,"source_type":4,"start_time":1759155937996},{"elapsed_time":212697,"interval":1,"segment":1,"source_type":4,"start_time":1759155938996},{"elapsed_time":213697,"interval":1,"segment":1,"source_type":4,"start_time":1759155939996},{"elapsed_time":214697,"interval":1,"segment":1,"source_type":4,"start_time":1759155940996},{"elapsed_time":215697,"interval":1,"segment":1,"source_type":4,"start_time":1759155941996},{"elapsed_time":216697,"interval":1,"segment":1,"source_type":4,"start_time":1759155942996},{"elapsed_time":217697,"interval":1,"segment":1,"source_type":4,"start_time":1759155943996},{"elapsed_time":218697,"interval":1,"segment":1,"source_type":4,"start_time":1759155944996},{"elapsed_time":219697,"interval":1,"segment":1,"source_type":4,"start_time":1759155945996},{"elapsed_time":220697,"interval":1,"segment":1,"source_type":4,"start_time":1759155946996},{"elapsed_time":221697,"interval":1,"segment":1,"source_type":4,"start_time":1759155947996},{"elapsed_time":222697,"interval":1,"segment":1,"source_type":4,"start_time":1759155948996},{"elapsed_time":223697,"interval":1,"segment":1,"source_type":4,"start_time":1759155949996},{"elapsed_time":224697,"interval":1,"segment":1,"source_type":4,"start_time":1759155950996},{"elapsed_time":225697,"interval":1,"segment":1,"source_type":4,"start_time":1759155951996},{"elapsed_time":226697,"interval":1,"segment":1,"source_type":4,"start_time":1759155952996},{"elapsed_time":227697,"interval":1,"segment":1,"source_type":4,"start_time":1759155953996},{"elapsed_time":228697,"interval":1,"segment":1,"source_type":4,"start_time":1759155954996},{"elapsed_time":229697,"interval":1,"segment":1,"source_type":4,"start_time":1759155955996},{"elapsed_time":230697,"interval":1,"segment":1,"source_type":4,"start_time":1759155956996},{"elapsed_time":231697,"interval":1,"segment":1,"source_type":4,"start_time":1759155957996},{"elapsed_time":232697,"interval":1,"segment":1,"source_type":4,"start_time":1759155958996},{"elapsed_time":233697,"interval":1,"segment":1,"source_type":4,"start_time":1759155959996},{"elapsed_time":234697,"interval":1,"segment":1,"source_type":4,"start_time":1759155960996},{"elapsed_time":235697,"interval":1,"segment":1,"source_type":4,"start_time":1759155961996},{"elapsed_time":236697,"interval":1,"segment":1,"source_type":4,"start_time":1759155962996},{"elapsed_time":237697,"interval":1,"segment":1,"source_type":4,"start_time":1759155963996},{"elapsed_time":238697,"interval":1,"segment":1,"source_type":4,"start_time":1759155964996},{"elapsed_time":239697,"interval":1,"segment":1,"source_type":4,"start_time":1759155965996},{"elapsed_time":240697,"interval":1,"segment":1,"source_type":4,"start_time":1759155966996},{"elapsed_time":241697,"interval":1,"segment":1,"source_type":4,"start_time":1759155967996},{"elapsed_time":242697,"interval":1,"segment":1,"source_type":4,"start_time":1759155968996},{"elapsed_time":243697,"interval":1,"segment":1,"source_type":4,"start_time":1759155969996},{"elapsed_time":244697,"interval":1,"segment":1,"source_type":4,"start_time":1759155970996},{"elapsed_time":245697,"interval":1,"segment":1,"source_type":4,"start_time":1759155971996},{"elapsed_time":246697,"interval":1,"segment":1,"source_type":4,"start_time":1759155972996},{"elapsed_time":247697,"interval":1,"segment":1,"source_type":4,"start_time":1759155973996},{"elapsed_time":248697,"interval":1,"segment":1,"source_type":4,"start_time":1759155974996},{"elapsed_time":249697,"interval":1,"segment":1,"source_type":4,"start_time":1759155975996},{"elapsed_time":250697,"interval":1,"segment":1,"source_type":4,"start_time":1759155976996},{"elapsed_time":251697,"interval":1,"segment":1,"source_type":4,"start_time":1759155977996},{"elapsed_time":252697,"interval":1,"segment":1,"source_type":4,"start_time":1759155978996},{"elapsed_time":253697,"interval":1,"segment":1,"source_type":4,"start_time":1759155979996},{"elapsed_time":254697,"interval":1,"segment":1,"source_type":4,"start_time":1759155980996},{"elapsed_time":255697,"interval":1,"segment":1,"source_type":4,"start_time":1759155981996},{"elapsed_time":256697,"interval":1,"segment":1,"source_type":4,"start_time":1759155982996},{"elapsed_time":257697,"interval":1,"segment":1,"source_type":4,"start_time":1759155983996},{"elapsed_time":258697,"interval":1,"segment":1,"source_type":4,"start_time":1759155984996},{"elapsed_time":259697,"interval":1,"segment":1,"source_type":4,"start_time":1759155985996},{"elapsed_time":260697,"interval":1,"segment":1,"source_type":4,"start_time":1759155986996},{"elapsed_time":261697,"interval":1,"segment":1,"source_type":4,"start_time":1759155987996},{"elapsed_time":262697,"interval":1,"segment":1,"source_type":4,"start_time":1759155988996},{"elapsed_time":263697,"interval":1,"segment":1,"source_type":4,"start_time":1759155989996},{"elapsed_time":264697,"interval":1,"segment":1,"source_type":4,"start_time":1759155990996},{"elapsed_time":265697,"interval":1,"segment":1,"source_type":4,"start_time":1759155991996},{"elapsed_time":266697,"interval":1,"segment":1,"source_type":4,"start_time":1759155992996},{"elapsed_time":268697,"interval":1,"segment":1,"source_type":4,"start_time":1759155994996},{"elapsed_time":269697,"interval":1,"segment":1,"source_type":4,"start_time":1759155995996},{"elapsed_time":270697,"interval":1,"segment":1,"source_type":4,"start_time":1759155996996},{"elapsed_time":271697,"interval":1,"segment":1,"source_type":4,"start_time":1759155997996},{"elapsed_time":272697,"interval":1,"segment":1,"source_type":4,"start_time":1759155998996},{"elapsed_time":273697,"interval":1,"segment":1,"source_type":4,"start_time":1759155999996},{"elapsed_time":274697,"interval":1,"segment":1,"source_type":4,"start_time":1759156000996},{"elapsed_time":275697,"interval":1,"segment":1,"source_type":4,"start_time":1759156001996},{"elapsed_time":276697,"interval":1,"segment":1,"source_type":4,"start_time":1759156002996},{"elapsed_time":277697,"interval":1,"segment":1,"source_type":4,"start_time":1759156003996},{"elapsed_time":278697,"interval":1,"segment":1,"source_type":4,"start_time":1759156004996},{"elapsed_time":279697,"interval":1,"segment":1,"source_type":4,"start_time":1759156005996},{"elapsed_time":280697,"interval":1,"segment":1,"source_type":4,"start_time":1759156006996},{"elapsed_time":281697,"interval":1,"segment":1,"source_type":4,"start_time":1759156007996},{"elapsed_time":282697,"interval":1,"segment":1,"source_type":4,"start_time":1759156008996},{"elapsed_time":283697,"interval":1,"segment":1,"source_type":4,"start_time":1759156009996},{"elapsed_time":284697,"interval":1,"segment":1,"source_type":4,"start_time":1759156010996},{"elapsed_time":285697,"interval":1,"segment":1,"source_type":4,"start_time":1759156011996},{"elapsed_time":286697,"interval":1,"segment":1,"source_type":4,"start_time":1759156012996},{"elapsed_time":287697,"interval":1,"segment":1,"source_type":4,"start_time":1759156013996},{"elapsed_time":288697,"interval":1,"segment":1,"source_type":4,"start_time":1759156014996},{"elapsed_time":289697,"interval":1,"segment":1,"source_type":4,"start_time":1759156015996},{"elapsed_time":290697,"interval":1,"segment":1,"source_type":4,"start_time":1759156016996},{"elapsed_time":291697,"interval":1,"segment":1,"source_type":4,"start_time":1759156017996},{"elapsed_time":292697,"interval":1,"segment":1,"source_type":4,"start_time":1759156018996},{"elapsed_time":293697,"interval":1,"segment":1,"source_type":4,"start_time":1759156019996},{"elapsed_time":294697,"interval":1,"segment":1,"source_type":4,"start_time":1759156020996},{"elapsed_time":295697,"interval":1,"segment":1,"source_type":4,"start_time":1759156021996},{"elapsed_time":296697,"interval":1,"segment":1,"source_type":4,"start_time":1759156022996},{"elapsed_time":297697,"interval":1,"segment":1,"source_type":4,"start_time":1759156023996},{"elapsed_time":298697,"interval":1,"segment":1,"source_type":4,"start_time":1759156024996},{"elapsed_time":299697,"interval":1,"segment":1,"source_type":4,"start_time":1759156025996},{"elapsed_time":300697,"interval":1,"segment":1,"source_type":4,"start_time":1759156026996},{"elapsed_time":301697,"interval":1,"segment":1,"source_type":4,"start_time":1759156027996},{"elapsed_time":302697,"interval":1,"segment":1,"source_type":4,"start_time":1759156028996},{"elapsed_time":303697,"interval":1,"segment":1,"source_type":4,"start_time":1759156029996},{"elapsed_time":304697,"interval":1,"segment":1,"source_type":4,"start_time":1759156030996},{"elapsed_time":305697,"interval":1,"segment":1,"source_type":4,"start_time":1759156031996},{"elapsed_time":306697,"interval":1,"segment":1,"source_type":4,"start_time":1759156032996},{"elapsed_time":307697,"interval":1,"segment":1,"source_type":4,"start_time":1759156033996},{"elapsed_time":308697,"interval":1,"segment":1,"source_type":4,"start_time":1759156034996},{"elapsed_time":309697,"interval":1,"segment":1,"source_type":4,"start_time":1759156035996},{"elapsed_time":310697,"interval":1,"segment":1,"source_type":4,"start_time":1759156036996},{"elapsed_time":311697,"interval":1,"segment":1,"source_type":4,"start_time":1759156037996},{"elapsed_time":312697,"interval":1,"segment":1,"source_type":4,"start_time":1759156038996},{"elapsed_time":313697,"interval":1,"segment":1,"source_type":4,"start_time":1759156039996},{"elapsed_time":314697,"interval":1,"segment":1,"source_type":4,"start_time":1759156040996},{"elapsed_time":315697,"interval":1,"segment":1,"source_type":4,"start_time":1759156041996},{"elapsed_time":316697,"interval":1,"segment":1,"source_type":4,"start_time":1759156042996},{"elapsed_time":317697,"interval":1,"segment":1,"source_type":4,"start_time":1759156043996},{"elapsed_time":318697,"interval":1,"segment":1,"source_type":4,"start_time":1759156044996},{"elapsed_time":319697,"interval":1,"segment":1,"source_type":4,"start_time":1759156045996},{"elapsed_time":320697,"interval":1,"segment":1,"source_type":4,"start_time":1759156046996},{"elapsed_time":321697,"interval":1,"segment":1,"source_type":4,"start_time":1759156047996},{"elapsed_time":322697,"interval":1,"segment":1,"source_type":4,"start_time":1759156048996},{"elapsed_time":323697,"interval":1,"segment":1,"source_type":4,"start_time":1759156049996},{"elapsed_time":324697,"interval":1,"segment":1,"source_type":4,"start_time":1759156050996},{"elapsed_time":325697,"interval":1,"segment":1,"source_type":4,"start_time":1759156051996},{"elapsed_time":326697,"interval":1,"segment":1,"source_type":4,"start_time":1759156052996},{"elapsed_time":327697,"interval":1,"segment":1,"source_type":4,"start_time":1759156053996},{"elapsed_time":328697,"interval":1,"segment":1,"source_type":4,"start_time":1759156054996},{"elapsed_time":329697,"interval":1,"segment":1,"source_type":4,"start_time":1759156055996},{"elapsed_time":330697,"interval":1,"segment":1,"source_type":4,"start_time":1759156056996},{"elapsed_time":331697,"interval":1,"segment":1,"source_type":4,"start_time":1759156057996},{"elapsed_time":332697,"interval":1,"segment":1,"source_type":4,"start_time":1759156058996},{"elapsed_time":333697,"interval":1,"segment":1,"source_type":4,"start_time":1759156059996},{"elapsed_time":334697,"interval":1,"segment":1,"source_type":4,"start_time":1759156060996},{"elapsed_time":335697,"interval":1,"segment":1,"source_type":4,"start_time":1759156061996},{"elapsed_time":336697,"interval":1,"segment":1,"source_type":4,"start_time":1759156062996},{"elapsed_time":337697,"interval":1,"segment":1,"source_type":4,"start_time":1759156063996},{"elapsed_time":338697,"interval":1,"segment":1,"source_type":4,"start_time":1759156064996},{"elapsed_time":339697,"interval":1,"segment":1,"source_type":4,"start_time":1759156065996},{"elapsed_time":340697,"interval":1,"segment":1,"source_type":4,"start_time":1759156066996},{"elapsed_time":341697,"interval":1,"segment":1,"source_type":4,"start_time":1759156067996},{"elapsed_time":342697,"interval":1,"segment":1,"source_type":4,"start_time":1759156068996},{"elapsed_time":343697,"interval":1,"segment":1,"source_type":4,"start_time":1759156069996},{"elapsed_time":344697,"interval":1,"segment":1,"source_type":4,"start_time":1759156070996},{"elapsed_time":345697,"interval":1,"segment":1,"source_type":4,"start_time":1759156071996},{"elapsed_time":346697,"interval":1,"segment":1,"source_type":4,"start_time":1759156072996},{"elapsed_time":347697,"interval":1,"segment":1,"source_type":4,"start_time":1759156073996},{"elapsed_time":348697,"interval":1,"segment":1,"source_type":4,"start_time":1759156074996},{"elapsed_time":349697,"interval":1,"segment":1,"source_type":4,"start_time":1759156075996},{"elapsed_time":350697,"interval":1,"segment":1,"source_type":4,"start_time":1759156076996},{"elapsed_time":351697,"interval":1,"segment":1,"source_type":4,"start_time":1759156077996},{"elapsed_time":352697,"interval":1,"segment":1,"source_type":4,"start_time":1759156078996},{"elapsed_time":353697,"interval":1,"segment":1,"source_type":4,"start_time":1759156079996},{"elapsed_time":354697,"interval":1,"segment":1,"source_type":4,"start_time":1759156080996},{"elapsed_time":355697,"interval":1,"segment":1,"source_type":4,"start_time":1759156081996},{"elapsed_time":356697,"interval":1,"segment":1,"source_type":4,"start_time":1759156082996},{"elapsed_time":357697,"interval":1,"segment":1,"source_type":4,"start_time":1759156083996},{"elapsed_time":358697,"interval":1,"segment":1,"source_type":4,"start_time":1759156084996},{"elapsed_time":359697,"interval":1,"segment":1,"source_type":4,"start_time":1759156085996},{"elapsed_time":360697,"interval":1,"segment":1,"source_type":4,"start_time":1759156086996},{"elapsed_time":361697,"interval":1,"segment":1,"source_type":4,"start_time":1759156087996},{"elapsed_time":362697,"interval":1,"segment":1,"source_type":4,"start_time":1759156088996},{"elapsed_time":363697,"interval":1,"segment":1,"source_type":4,"start_time":1759156089996},{"elapsed_time":364697,"interval":1,"segment":1,"source_type":4,"start_time":1759156090996},{"elapsed_time":365697,"interval":1,"segment":1,"source_type":4,"start_time":1759156091996},{"elapsed_time":366697,"interval":1,"segment":1,"source_type":4,"start_time":1759156092996},{"elapsed_time":367697,"interval":1,"segment":1,"source_type":4,"start_time":1759156093996},{"elapsed_time":368697,"interval":1,"segment":1,"source_type":4,"start_time":1759156094996},{"elapsed_time":369697,"interval":1,"segment":1,"source_type":4,"start_time":1759156095996},{"elapsed_time":370697,"interval":1,"segment":1,"source_type":4,"start_time":1759156096996},{"elapsed_time":371697,"interval":1,"segment":1,"source_type":4,"start_time":1759156097996},{"elapsed_time":372697,"interval":1,"segment":1,"source_type":4,"start_time":1759156098996},{"elapsed_time":373697,"interval":1,"segment":1,"source_type":4,"start_time":1759156099996},{"elapsed_time":374697,"interval":1,"segment":1,"source_type":4,"start_time":1759156100996},{"elapsed_time":375697,"interval":1,"segment":1,"source_type":4,"start_time":1759156101996},{"elapsed_time":376697,"interval":1,"segment":1,"source_type":4,"start_time":1759156102996},{"elapsed_time":377697,"interval":1,"segment":1,"source_type":4,"start_time":1759156103996},{"elapsed_time":378697,"interval":1,"segment":1,"source_type":4,"start_time":1759156104996},{"elapsed_time":379697,"interval":1,"segment":1,"source_type":4,"start_time":1759156105996},{"elapsed_time":380697,"interval":1,"segment":1,"source_type":4,"start_time":1759156106996},{"elapsed_time":381697,"interval":1,"segment":1,"source_type":4,"start_time":1759156107996},{"elapsed_time":382697,"interval":1,"segment":1,"source_type":4,"start_time":1759156108996},{"elapsed_time":383697,"interval":1,"segment":1,"source_type":4,"start_time":1759156109996},{"elapsed_time":384697,"interval":1,"segment":1,"source_type":4,"start_time":1759156110996},{"elapsed_time":385697,"interval":1,"segment":1,"source_type":4,"start_time":1759156111996},{"elapsed_time":386697,"interval":1,"segment":1,"source_type":4,"start_time":1759156112996},{"elapsed_time":387697,"interval":1,"segment":1,"source_type":4,"start_time":1759156113996},{"elapsed_time":388697,"interval":1,"segment":1,"source_type":4,"start_time":1759156114996},{"elapsed_time":389697,"interval":1,"segment":1,"source_type":4,"start_time":1759156115996},{"elapsed_time":390697,"interval":1,"segment":1,"source_type":4,"start_time":1759156116996},{"elapsed_time":391697,"interval":1,"segment":1,"source_type":4,"start_time":1759156117996},{"elapsed_time":392697,"interval":1,"segment":1,"source_type":4,"start_time":1759156118996},{"elapsed_time":393697,"interval":1,"segment":1,"source_type":4,"start_time":1759156119996},{"elapsed_time":394697,"interval":1,"segment":1,"source_type":4,"start_time":1759156120996},{"elapsed_time":395697,"interval":1,"segment":1,"source_type":4,"start_time":1759156121996},{"elapsed_time":396697,"interval":1,"segment":1,"source_type":4,"start_time":1759156122996},{"elapsed_time":397697,"interval":1,"segment":1,"source_type":4,"start_time":1759156123996},{"elapsed_time":398697,"interval":1,"segment":1,"source_type":4,"start_time":1759156124996},{"elapsed_time":399697,"interval":1,"segment":1,"source_type":4,"start_time":1759156125996},{"elapsed_time":400697,"interval":1,"segment":1,"source_type":4,"start_time":1759156126996},{"elapsed_time":401697,"interval":1,"segment":1,"source_type":4,"start_time":1759156127996},{"elapsed_time":402697,"interval":1,"segment":1,"source_type":4,"start_time":1759156128996},{"elapsed_time":403697,"interval":1,"segment":1,"source_type":4,"start_time":1759156129996},{"elapsed_time":404697,"interval":1,"segment":1,"source_type":4,"start_time":1759156130996},{"elapsed_time":405697,"interval":1,"segment":1,"source_type":4,"start_time":1759156131996},{"elapsed_time":406697,"interval":1,"segment":1,"source_type":4,"start_time":1759156132996},{"elapsed_time":407697,"interval":1,"segment":1,"source_type":4,"start_time":1759156133996},{"elapsed_time":408697,"interval":1,"segment":1,"source_type":4,"start_time":1759156134996},{"elapsed_time":409697,"interval":1,"segment":1,"source_type":4,"start_time":1759156135996},{"elapsed_time":410697,"interval":1,"segment":1,"source_type":4,"start_time":1759156136996},{"elapsed_time":411697,"interval":1,"segment":1,"source_type":4,"start_time":1759156137996},{"elapsed_time":412697,"interval":1,"segment":1,"source_type":4,"start_time":1759156138996},{"elapsed_time":413697,"interval":1,"segment":1,"source_type":4,"start_time":1759156139996},{"elapsed_time":414697,"interval":1,"segment":1,"source_type":4,"start_time":1759156140996},{"elapsed_time":415697,"interval":1,"segment":1,"source_type":4,"start_time":1759156141996},{"elapsed_time":416697,"interval":1,"segment":1,"source_type":4,"start_time":1759156142996},{"elapsed_time":417697,"interval":1,"segment":1,"source_type":4,"start_time":1759156143996},{"elapsed_time":418697,"interval":1,"segment":1,"source_type":4,"start_time":1759156144996},{"elapsed_time":419697,"interval":1,"segment":1,"source_type":4,"start_time":1759156145996},{"elapsed_time":420697,"interval":1,"segment":1,"source_type":4,"start_time":1759156146996},{"elapsed_time":421697,"interval":1,"segment":1,"source_type":4,"start_time":1759156147996},{"elapsed_time":422697,"interval":1,"segment":1,"source_type":4,"start_time":1759156148996},{"elapsed_time":423697,"interval":1,"segment":1,"source_type":4,"start_time":1759156149996},{"elapsed_time":424697,"interval":1,"segment":1,"source_type":4,"start_time":1759156150996},{"elapsed_time":425697,"interval":1,"segment":1,"source_type":4,"start_time":1759156151996},{"elapsed_time":426697,"interval":1,"segment":1,"source_type":4,"start_time":1759156152996},{"elapsed_time":427697,"interval":1,"segment":1,"source_type":4,"start_time":1759156153996},{"elapsed_time":428697,"interval":1,"segment":1,"source_type":4,"start_time":1759156154996},{"elapsed_time":429697,"interval":1,"segment":1,"source_type":4,"start_time":1759156155996},{"elapsed_time":430697,"interval":1,"segment":1,"source_type":4,"start_time":1759156156996},{"elapsed_time":431697,"interval":1,"segment":1,"source_type":4,"start_time":1759156157996},{"elapsed_time":432697,"interval":1,"segment":1,"source_type":4,"start_time":1759156158996},{"elapsed_time":433697,"interval":1,"segment":1,"source_type":4,"start_time":1759156159996},{"elapsed_time":434697,"interval":1,"segment":1,"source_type":4,"start_time":1759156160996},{"elapsed_time":435697,"interval":1,"segment":1,"source_type":4,"start_time":1759156161996},{"elapsed_time":436697,"interval":1,"segment":1,"source_type":4,"start_time":1759156162996},{"elapsed_time":437697,"interval":1,"segment":1,"source_type":4,"start_time":1759156163996},{"elapsed_time":438697,"interval":1,"segment":1,"source_type":4,"start_time":1759156164996},{"elapsed_time":439697,"interval":1,"segment":1,"source_type":4,"start_time":1759156165996},{"elapsed_time":440697,"interval":1,"segment":1,"source_type":4,"start_time":1759156166996},{"elapsed_time":441697,"interval":1,"segment":1,"source_type":4,"start_time":1759156167996},{"elapsed_time":442697,"interval":1,"segment":1,"source_type":4,"start_time":1759156168996},{"elapsed_time":443697,"interval":1,"segment":1,"source_type":4,"start_time":1759156169996},{"elapsed_time":444697,"interval":1,"segment":1,"source_type":4,"start_time":1759156170996},{"elapsed_time":445697,"interval":1,"segment":1,"source_type":4,"start_time":1759156171996},{"elapsed_time":446697,"interval":1,"segment":1,"source_type":4,"start_time":1759156172996},{"elapsed_time":447697,"interval":1,"segment":1,"source_type":4,"start_time":1759156173996},{"elapsed_time":448697,"interval":1,"segment":1,"source_type":4,"start_time":1759156174996},{"elapsed_time":449697,"interval":1,"segment":1,"source_type":4,"start_time":1759156175996},{"elapsed_time":450697,"interval":1,"segment":1,"source_type":4,"start_time":1759156176996},{"elapsed_time":451697,"interval":1,"segment":1,"source_type":4,"start_time":1759156177996},{"elapsed_time":452697,"interval":1,"segment":1,"source_type":4,"start_time":1759156178996},{"elapsed_time":453697,"interval":1,"segment":1,"source_type":4,"start_time":1759156179996},{"elapsed_time":454697,"interval":1,"segment":1,"source_type":4,"start_time":1759156180996},{"elapsed_time":455697,"interval":1,"segment":1,"source_type":4,"start_time":1759156181996},{"elapsed_time":456697,"interval":1,"segment":1,"source_type":4,"start_time":1759156182996},{"elapsed_time":457697,"interval":1,"segment":1,"source_type":4,"start_time":1759156183996},{"elapsed_time":458697,"interval":1,"segment":1,"source_type":4,"start_time":1759156184996},{"elapsed_time":459697,"interval":1,"segment":1,"source_type":4,"start_time":1759156185996},{"elapsed_time":460697,"interval":1,"segment":1,"source_type":4,"start_time":1759156186996},{"elapsed_time":461697,"interval":1,"segment":1,"source_type":4,"start_time":1759156187996},{"elapsed_time":462697,"interval":1,"segment":1,"source_type":4,"start_time":1759156188996},{"elapsed_time":463697,"interval":1,"segment":1,"source_type":4,"start_time":1759156189996},{"elapsed_time":464697,"interval":1,"segment":1,"source_type":4,"start_time":1759156190996},{"elapsed_time":465697,"interval":1,"segment":1,"source_type":4,"start_time":1759156191996},{"elapsed_time":466697,"interval":1,"segment":1,"source_type":4,"start_time":1759156192996},{"elapsed_time":467697,"interval":1,"segment":1,"source_type":4,"start_time":1759156193996},{"elapsed_time":468697,"interval":1,"segment":1,"source_type":4,"start_time":1759156194996},{"elapsed_time":469697,"interval":1,"segment":1,"source_type":4,"start_time":1759156195996},{"elapsed_time":470697,"interval":1,"segment":1,"source_type":4,"start_time":1759156196996},{"elapsed_time":471697,"interval":1,"segment":1,"source_type":4,"start_time":1759156197996},{"elapsed_time":473697,"interval":1,"segment":1,"source_type":4,"start_time":1759156199996},{"elapsed_time":474697,"interval":1,"segment":1,"source_type":4,"start_time":1759156200996},{"elapsed_time":475697,"interval":1,"segment":1,"source_type":4,"start_time":1759156201996},{"elapsed_time":476697,"interval":1,"segment":1,"source_type":4,"start_time":1759156202996},{"elapsed_time":477697,"interval":1,"segment":1,"source_type":4,"start_time":1759156203996},{"elapsed_time":478697,"interval":1,"segment":1,"source_type":4,"start_time":1759156204996},{"elapsed_time":479697,"interval":1,"segment":1,"source_type":4,"start_time":1759156205996},{"elapsed_time":480697,"interval":1,"segment":1,"source_type":4,"start_time":1759156206996},{"elapsed_time":481697,"interval":1,"segment":1,"source_type":4,"start_time":1759156207996},{"elapsed_time":482697,"interval":1,"segment":1,"source_type":4,"start_time":1759156208996},{"elapsed_time":483697,"interval":1,"segment":1,"source_type":4,"start_time":1759156209996},{"elapsed_time":484697,"interval":1,"segment":1,"source_type":4,"start_time":1759156210996},{"elapsed_time":485697,"interval":1,"segment":1,"source_type":4,"start_time":1759156211996},{"elapsed_time":486697,"interval":1,"segment":1,"source_type":4,"start_time":1759156212996},{"elapsed_time":487697,"interval":1,"segment":1,"source_type":4,"start_time":1759156213996},{"elapsed_time":488697,"interval":1,"segment":1,"source_type":4,"start_time":1759156214996},{"elapsed_time":489697,"interval":1,"segment":1,"source_type":4,"start_time":1759156215996},{"elapsed_time":490697,"interval":1,"segment":1,"source_type":4,"start_time":1759156216996},{"elapsed_time":491697,"interval":1,"segment":1,"source_type":4,"start_time":1759156217996},{"elapsed_time":492697,"interval":1,"segment":1,"source_type":4,"start_time":1759156218996},{"elapsed_time":493697,"interval":1,"segment":1,"source_type":4,"start_time":1759156219996},{"elapsed_time":494697,"interval":1,"segment":1,"source_type":4,"start_time":1759156220996},{"elapsed_time":496697,"interval":1,"segment":1,"source_type":4,"start_time":1759156222996},{"elapsed_time":497697,"interval":1,"segment":1,"source_type":4,"start_time":1759156223996},{"elapsed_time":498697,"interval":1,"segment":1,"source_type":4,"start_time":1759156224996},{"elapsed_time":499697,"interval":1,"segment":1,"source_type":4,"start_time":1759156225996},{"elapsed_time":500697,"interval":1,"segment":1,"source_type":4,"start_time":1759156226996},{"elapsed_time":501697,"interval":1,"segment":1,"source_type":4,"start_time":1759156227996},{"elapsed_time":502697,"interval":1,"segment":1,"source_type":4,"start_time":1759156228996},{"elapsed_time":503697,"interval":1,"segment":1,"source_type":4,"start_time":1759156229996},{"elapsed_time":504697,"interval":1,"segment":1,"source_type":4,"start_time":1759156230996},{"elapsed_time":505697,"interval":1,"segment":1,"source_type":4,"start_time":1759156231996},{"elapsed_time":506697,"interval":1,"segment":1,"source_type":4,"start_time":1759156232996},{"elapsed_time":507697,"interval":1,"segment":1,"source_type":4,"start_time":1759156233996},{"elapsed_time":508697,"interval":1,"segment":1,"source_type":4,"start_time":1759156234996},{"elapsed_time":509697,"interval":1,"segment":1,"source_type":4,"start_time":1759156235996},{"elapsed_time":510697,"interval":1,"segment":1,"source_type":4,"start_time":1759156236996},{"elapsed_time":511697,"interval":1,"segment":1,"source_type":4,"start_time":1759156237996},{"elapsed_time":512697,"interval":1,"segment":1,"source_type":4,"start_time":1759156238996},{"elapsed_time":513697,"interval":1,"segment":1,"source_type":4,"start_time":1759156239996},{"elapsed_time":514697,"interval":1,"segment":1,"source_type":4,"start_time":1759156240996},{"elapsed_time":515697,"interval":1,"segment":1,"source_type":4,"start_time":1759156241996},{"elapsed_time":516697,"interval":1,"segment":1,"source_type":4,"start_time":1759156242996},{"elapsed_time":517854,"interval":1,"segment":1,"source_type":4,"start_time":1759156244153},{"elapsed_time":518854,"interval":1,"segment":1,"source_type":4,"start_time":1759156245153},{"elapsed_time":519854,"interval":1,"segment":1,"source_type":4,"start_time":1759156246153},{"elapsed_time":520854,"interval":1,"segment":1,"source_type":4,"start_time":1759156247153},{"elapsed_time":521854,"interval":1,"segment":1,"source_type":4,"start_time":1759156248153},{"elapsed_time":522854,"interval":1,"segment":1,"source_type":4,"start_time":1759156249153},{"elapsed_time":523854,"interval":1,"segment":1,"source_type":4,"start_time":1759156250153},{"elapsed_time":524854,"interval":1,"segment":1,"source_type":4,"start_time":1759156251153},{"elapsed_time":525854,"interval":1,"segment":1,"source_type":4,"start_time":1759156252153},{"elapsed_time":526854,"interval":1,"segment":1,"source_type":4,"start_time":1759156253153},{"elapsed_time":527854,"interval":1,"segment":1,"source_type":4,"start_time":1759156254153},{"elapsed_time":528854,"interval":1,"segment":1,"source_type":4,"start_time":1759156255153},{"elapsed_time":529854,"interval":1,"segment":1,"source_type":4,"start_time":1759156256153},{"elapsed_time":530854,"interval":1,"segment":1,"source_type":4,"start_time":1759156257153},{"elapsed_time":531854,"interval":1,"segment":1,"source_type":4,"start_time":1759156258153},{"elapsed_time":532854,"interval":1,"segment":1,"source_type":4,"start_time":1759156259153},{"elapsed_time":533854,"interval":1,"segment":1,"source_type":4,"start_time":1759156260153},{"elapsed_time":534854,"interval":1,"segment":1,"source_type":4,"start_time":1759156261153},{"elapsed_time":535854,"interval":1,"segment":1,"source_type":4,"start_time":1759156262153},{"elapsed_time":536854,"interval":1,"segment":1,"source_type":4,"start_time":1759156263153},{"elapsed_time":537854,"interval":1,"segment":1,"source_type":4,"start_time":1759156264153},{"elapsed_time":151697,"interval":1,"segment":1,"source_type":4,"start_time":1759155877996},{"elapsed_time":152697,"interval":1,"segment":1,"source_type":4,"start_time":1759155878996},{"elapsed_time":153697,"interval":1,"segment":1,"source_type":4,"start_time":1759155879996},{"elapsed_time":154697,"interval":1,"segment":1,"source_type":4,"start_time":1759155880996},{"elapsed_time":155697,"interval":1,"segment":1,"source_type":4,"start_time":1759155881996},{"elapsed_time":156697,"interval":1,"segment":1,"source_type":4,"start_time":1759155882996},{"elapsed_time":157697,"interval":1,"segment":1,"source_type":4,"start_time":1759155883996},{"elapsed_time":158697,"interval":1,"segment":1,"source_type":4,"start_time":1759155884996},{"elapsed_time":159697,"interval":1,"segment":1,"source_type":4,"start_time":1759155885996},{"elapsed_time":160697,"interval":1,"segment":1,"source_type":4,"start_time":1759155886996},{"elapsed_time":161697,"interval":1,"segment":1,"source_type":4,"start_time":1759155887996},{"elapsed_time":162697,"interval":1,"segment":1,"source_type":4,"start_time":1759155888996},{"elapsed_time":163697,"interval":1,"segment":1,"source_type":4,"start_time":1759155889996},{"elapsed_time":164697,"interval":1,"segment":1,"source_type":4,"start_time":1759155890996},{"elapsed_time":165697,"interval":1,"segment":1,"source_type":4,"start_time":1759155891996},{"elapsed_time":166697,"interval":1,"segment":1,"source_type":4,"start_time":1759155892996},{"elapsed_time":167697,"interval":1,"segment":1,"source_type":4,"start_time":1759155893996},{"elapsed_time":168697,"interval":1,"segment":1,"source_type":4,"start_time":1759155894996},{"elapsed_time":169697,"interval":1,"segment":1,"source_type":4,"start_time":1759155895996},{"elapsed_time":170697,"interval":1,"segment":1,"source_type":4,"start_time":1759155896996},{"elapsed_time":171697,"interval":1,"segment":1,"source_type":4,"start_time":1759155897996},{"elapsed_time":172697,"interval":1,"segment":1,"source_type":4,"start_time":1759155898996},{"elapsed_time":173697,"interval":1,"segment":1,"source_type":4,"start_time":1759155899996},{"elapsed_time":174697,"interval":1,"segment":1,"source_type":4,"start_time":1759155900996},{"elapsed_time":175697,"interval":1,"segment":1,"source_type":4,"start_time":1759155901996},{"elapsed_time":176697,"interval":1,"segment":1,"source_type":4,"start_time":1759155902996},{"elapsed_time":177697,"interval":1,"segment":1,"source_type":4,"start_time":1759155903996},{"elapsed_time":178697,"interval":1,"segment":1,"source_type":4,"start_time":1759155904996},{"elapsed_time":179697,"interval":1,"segment":1,"source_type":4,"start_time":1759155905996},{"elapsed_time":180697,"interval":1,"segment":1,"source_type":4,"start_time":1759155906996},{"elapsed_time":181697,"interval":1,"segment":1,"source_type":4,"start_time":1759155907996},{"elapsed_time":182697,"interval":1,"segment":1,"source_type":4,"start_time":1759155908996},{"elapsed_time":183697,"interval":1,"segment":1,"source_type":4,"start_time":1759155909996},{"elapsed_time":184697,"interval":1,"segment":1,"source_type":4,"start_time":1759155910996},{"elapsed_time":185697,"interval":1,"segment":1,"source_type":4,"start_time":1759155911996},{"elapsed_time":186697,"interval":1,"segment":1,"source_type":4,"start_time":1759155912996},{"elapsed_time":187697,"interval":1,"segment":1,"source_type":4,"start_time":1759155913996},{"elapsed_time":188697,"interval":1,"segment":1,"source_type":4,"start_time":1759155914996},{"elapsed_time":189697,"interval":1,"segment":1,"source_type":4,"start_time":1759155915996},{"elapsed_time":190697,"interval":1,"segment":1,"source_type":4,"start_time":1759155916996},{"elapsed_time":191697,"interval":1,"segment":1,"source_type":4,"start_time":1759155917996},{"elapsed_time":192697,"interval":1,"segment":1,"source_type":4,"start_time":1759155918996},{"elapsed_time":193697,"interval":1,"segment":1,"source_type":4,"start_time":1759155919996},{"elapsed_time":194697,"interval":1,"segment":1,"source_type":4,"start_time":1759155920996},{"elapsed_time":195697,"interval":1,"segment":1,"source_type":4,"start_time":1759155921996},{"elapsed_time":196697,"interval":1,"segment":1,"source_type":4,"start_time":1759155922996},{"elapsed_time":197697,"interval":1,"segment":1,"source_type":4,"start_time":1759155923996},{"elapsed_time":198697,"interval":1,"segment":1,"source_type":4,"start_time":1759155924996},{"elapsed_time":199697,"interval":1,"segment":1,"source_type":4,"start_time":1759155925996},{"elapsed_time":200697,"interval":1,"segment":1,"source_type":4,"start_time":1759155926996},{"elapsed_time":201697,"interval":1,"segment":1,"source_type":4,"start_time":1759155927996},{"elapsed_time":202697,"interval":1,"segment":1,"source_type":4,"start_time":1759155928996},{"elapsed_time":203697,"interval":1,"segment":1,"source_type":4,"start_time":1759155929996},{"elapsed_time":204697,"interval":1,"segment":1,"source_type":4,"start_time":1759155930996},{"elapsed_time":205697,"interval":1,"segment":1,"source_type":4,"start_time":1759155931996},{"elapsed_time":206697,"interval":1,"segment":1,"source_type":4,"start_time":1759155932996},{"elapsed_time":207697,"interval":1,"segment":1,"source_type":4,"start_time":1759155933996},{"elapsed_time":208697,"interval":1,"segment":1,"source_type":4,"start_time":1759155934996},{"elapsed_time":209697,"interval":1,"segment":1,"source_type":4,"start_time":1759155935996},{"elapsed_time":210697,"interval":1,"segment":1,"source_type":4,"start_time":1759155936996},{"elapsed_time":211697,"interval":1,"segment":1,"source_type":4,"start_time":1759155937996},{"elapsed_time":212697,"interval":1,"segment":1,"source_type":4,"start_time":1759155938996},{"elapsed_time":213697,"interval":1,"segment":1,"source_type":4,"start_time":1759155939996},{"elapsed_time":214697,"interval":1,"segment":1,"source_type":4,"start_time":1759155940996},{"elapsed_time":215697,"interval":1,"segment":1,"source_type":4,"start_time":1759155941996},{"elapsed_time":216697,"interval":1,"segment":1,"source_type":4,"start_time":1759155942996},{"elapsed_time":217697,"interval":1,"segment":1,"source_type":4,"start_time":1759155943996},{"elapsed_time":218697,"interval":1,"segment":1,"source_type":4,"start_time":1759155944996},{"elapsed_time":219697,"interval":1,"segment":1,"source_type":4,"start_time":1759155945996},{"elapsed_time":220697,"interval":1,"segment":1,"source_type":4,"start_time":1759155946996},{"elapsed_time":221697,"interval":1,"segment":1,"source_type":4,"start_time":1759155947996},{"elapsed_time":222697,"interval":1,"segment":1,"source_type":4,"start_time":1759155948996},{"elapsed_time":223697,"interval":1,"segment":1,"source_type":4,"start_time":1759155949996},{"elapsed_time":224697,"interval":1,"segment":1,"source_type":4,"start_time":1759155950996},{"elapsed_time":225697,"interval":1,"segment":1,"source_type":4,"start_time":1759155951996},{"elapsed_time":226697,"interval":1,"segment":1,"source_type":4,"start_time":1759155952996},{"elapsed_time":227697,"interval":1,"segment":1,"source_type":4,"start_time":1759155953996},{"elapsed_time":228697,"interval":1,"segment":1,"source_type":4,"start_time":1759155954996},{"elapsed_time":229697,"interval":1,"segment":1,"source_type":4,"start_time":1759155955996},{"elapsed_time":230697,"interval":1,"segment":1,"source_type":4,"start_time":1759155956996},{"elapsed_time":231697,"interval":1,"segment":1,"source_type":4,"start_time":1759155957996},{"elapsed_time":232697,"interval":1,"segment":1,"source_type":4,"start_time":1759155958996},{"elapsed_time":233697,"interval":1,"segment":1,"source_type":4,"start_time":1759155959996},{"elapsed_time":234697,"interval":1,"segment":1,"source_type":4,"start_time":1759155960996},{"elapsed_time":235697,"interval":1,"segment":1,"source_type":4,"start_time":1759155961996},{"elapsed_time":236697,"interval":1,"segment":1,"source_type":4,"start_time":1759155962996},{"elapsed_time":237697,"interval":1,"segment":1,"source_type":4,"start_time":1759155963996},{"elapsed_time":238697,"interval":1,"segment":1,"source_type":4,"start_time":1759155964996},{"elapsed_time":239697,"interval":1,"segment":1,"source_type":4,"start_time":1759155965996},{"elapsed_time":240697,"interval":1,"segment":1,"source_type":4,"start_time":1759155966996},{"elapsed_time":241697,"interval":1,"segment":1,"source_type":4,"start_time":1759155967996},{"elapsed_time":242697,"interval":1,"segment":1,"source_type":4,"start_time":1759155968996},{"elapsed_time":243697,"interval":1,"segment":1,"source_type":4,"start_time":1759155969996},{"elapsed_time":244697,"interval":1,"segment":1,"source_type":4,"start_time":1759155970996},{"elapsed_time":245697,"interval":1,"segment":1,"source_type":4,"start_time":1759155971996},{"elapsed_time":246697,"interval":1,"segment":1,"source_type":4,"start_time":1759155972996},{"elapsed_time":247697,"interval":1,"segment":1,"source_type":4,"start_time":1759155973996},{"elapsed_time":248697,"interval":1,"segment":1,"source_type":4,"start_time":1759155974996},{"elapsed_time":249697,"interval":1,"segment":1,"source_type":4,"start_time":1759155975996},{"elapsed_time":250697,"interval":1,"segment":1,"source_type":4,"start_time":1759155976996},{"elapsed_time":251697,"interval":1,"segment":1,"source_type":4,"start_time":1759155977996},{"elapsed_time":252697,"interval":1,"segment":1,"source_type":4,"start_time":1759155978996},{"elapsed_time":253697,"interval":1,"segment":1,"source_type":4,"start_time":1759155979996},{"elapsed_time":254697,"interval":1,"segment":1,"source_type":4,"start_time":1759155980996},{"elapsed_time":255697,"interval":1,"segment":1,"source_type":4,"start_time":1759155981996},{"elapsed_time":256697,"interval":1,"segment":1,"source_type":4,"start_time":1759155982996},{"elapsed_time":257697,"interval":1,"segment":1,"source_type":4,"start_time":1759155983996},{"elapsed_time":258697,"interval":1,"segment":1,"source_type":4,"start_time":1759155984996},{"elapsed_time":259697,"interval":1,"segment":1,"source_type":4,"start_time":1759155985996},{"elapsed_time":260697,"interval":1,"segment":1,"source_type":4,"start_time":1759155986996},{"elapsed_time":261697,"interval":1,"segment":1,"source_type":4,"start_time":1759155987996},{"elapsed_time":262697,"interval":1,"segment":1,"source_type":4,"start_time":1759155988996},{"elapsed_time":263697,"interval":1,"segment":1,"source_type":4,"start_time":1759155989996},{"elapsed_time":264697,"interval":1,"segment":1,"source_type":4,"start_time":1759155990996},{"elapsed_time":265697,"interval":1,"segment":1,"source_type":4,"start_time":1759155991996},{"elapsed_time":266697,"interval":1,"segment":1,"source_type":4,"start_time":1759155992996},{"elapsed_time":268697,"interval":1,"segment":1,"source_type":4,"start_time":1759155994996},{"elapsed_time":269697,"interval":1,"segment":1,"source_type":4,"start_time":1759155995996},{"elapsed_time":270697,"interval":1,"segment":1,"source_type":4,"start_time":1759155996996},{"elapsed_time":271697,"interval":1,"segment":1,"source_type":4,"start_time":1759155997996},{"elapsed_time":272697,"interval":1,"segment":1,"source_type":4,"start_time":1759155998996},{"elapsed_time":273697,"interval":1,"segment":1,"source_type":4,"start_time":1759155999996},{"elapsed_time":274697,"interval":1,"segment":1,"source_type":4,"start_time":1759156000996},{"elapsed_time":275697,"interval":1,"segment":1,"source_type":4,"start_time":1759156001996},{"elapsed_time":276697,"interval":1,"segment":1,"source_type":4,"start_time":1759156002996},{"elapsed_time":277697,"interval":1,"segment":1,"source_type":4,"start_time":1759156003996},{"elapsed_time":278697,"interval":1,"segment":1,"source_type":4,"start_time":1759156004996},{"elapsed_time":279697,"interval":1,"segment":1,"source_type":4,"start_time":1759156005996},{"elapsed_time":280697,"interval":1,"segment":1,"source_type":4,"start_time":1759156006996},{"elapsed_time":281697,"interval":1,"segment":1,"source_type":4,"start_time":1759156007996},{"elapsed_time":282697,"interval":1,"segment":1,"source_type":4,"start_time":1759156008996},{"elapsed_time":283697,"interval":1,"segment":1,"source_type":4,"start_time":1759156009996},{"elapsed_time":284697,"interval":1,"segment":1,"source_type":4,"start_time":1759156010996},{"elapsed_time":285697,"interval":1,"segment":1,"source_type":4,"start_time":1759156011996},{"elapsed_time":286697,"interval":1,"segment":1,"source_type":4,"start_time":1759156012996},{"elapsed_time":287697,"interval":1,"segment":1,"source_type":4,"start_time":1759156013996},{"elapsed_time":288697,"interval":1,"segment":1,"source_type":4,"start_time":1759156014996},{"elapsed_time":289697,"interval":1,"segment":1,"source_type":4,"start_time":1759156015996},{"elapsed_time":290697,"interval":1,"segment":1,"source_type":4,"start_time":1759156016996},{"elapsed_time":291697,"interval":1,"segment":1,"source_type":4,"start_time":1759156017996},{"elapsed_time":292697,"interval":1,"segment":1,"source_type":4,"start_time":1759156018996},{"elapsed_time":293697,"interval":1,"segment":1,"source_type":4,"start_time":1759156019996},{"elapsed_time":294697,"interval":1,"segment":1,"source_type":4,"start_time":1759156020996},{"elapsed_time":295697,"interval":1,"segment":1,"source_type":4,"start_time":1759156021996},{"elapsed_time":296697,"interval":1,"segment":1,"source_type":4,"start_time":1759156022996},{"elapsed_time":297697,"interval":1,"segment":1,"source_type":4,"start_time":1759156023996},{"elapsed_time":298697,"interval":1,"segment":1,"source_type":4,"start_time":1759156024996},{"elapsed_time":299697,"interval":1,"segment":1,"source_type":4,"start_time":1759156025996},{"elapsed_time":300697,"interval":1,"segment":1,"source_type":4,"start_time":1759156026996},{"elapsed_time":301697,"interval":1,"segment":1,"source_type":4,"start_time":1759156027996},{"elapsed_time":302697,"interval":1,"segment":1,"source_type":4,"start_time":1759156028996},{"elapsed_time":303697,"interval":1,"segment":1,"source_type":4,"start_time":1759156029996},{"elapsed_time":304697,"interval":1,"segment":1,"source_type":4,"start_time":1759156030996},{"elapsed_time":305697,"interval":1,"segment":1,"source_type":4,"start_time":1759156031996},{"elapsed_time":306697,"interval":1,"segment":1,"source_type":4,"start_time":1759156032996},{"elapsed_time":307697,"interval":1,"segment":1,"source_type":4,"start_time":1759156033996},{"elapsed_time":308697,"interval":1,"segment":1,"source_type":4,"start_time":1759156034996},{"elapsed_time":309697,"interval":1,"segment":1,"source_type":4,"start_time":1759156035996},{"elapsed_time":310697,"interval":1,"segment":1,"source_type":4,"start_time":1759156036996},{"elapsed_time":311697,"interval":1,"segment":1,"source_type":4,"start_time":1759156037996},{"elapsed_time":312697,"interval":1,"segment":1,"source_type":4,"start_time":1759156038996},{"elapsed_time":313697,"interval":1,"segment":1,"source_type":4,"start_time":1759156039996},{"elapsed_time":314697,"interval":1,"segment":1,"source_type":4,"start_time":1759156040996},{"elapsed_time":315697,"interval":1,"segment":1,"source_type":4,"start_time":1759156041996},{"elapsed_time":316697,"interval":1,"segment":1,"source_type":4,"start_time":1759156042996},{"elapsed_time":317697,"interval":1,"segment":1,"source_type":4,"start_time":1759156043996},{"elapsed_time":318697,"interval":1,"segment":1,"source_type":4,"start_time":1759156044996},{"elapsed_time":319697,"interval":1,"segment":1,"source_type":4,"start_time":1759156045996},{"elapsed_time":320697,"interval":1,"segment":1,"source_type":4,"start_time":1759156046996},{"elapsed_time":321697,"interval":1,"segment":1,"source_type":4,"start_time":1759156047996},{"elapsed_time":322697,"interval":1,"segment":1,"source_type":4,"start_time":1759156048996},{"elapsed_time":323697,"interval":1,"segment":1,"source_type":4,"start_time":1759156049996},{"elapsed_time":324697,"interval":1,"segment":1,"source_type":4,"start_time":1759156050996},{"elapsed_time":325697,"interval":1,"segment":1,"source_type":4,"start_time":1759156051996},{"elapsed_time":326697,"interval":1,"segment":1,"source_type":4,"start_time":1759156052996},{"elapsed_time":327697,"interval":1,"segment":1,"source_type":4,"start_time":1759156053996},{"elapsed_time":328697,"interval":1,"segment":1,"source_type":4,"start_time":1759156054996},{"elapsed_time":329697,"interval":1,"segment":1,"source_type":4,"start_time":1759156055996},{"elapsed_time":330697,"interval":1,"segment":1,"source_type":4,"start_time":1759156056996},{"elapsed_time":331697,"interval":1,"segment":1,"source_type":4,"start_time":1759156057996},{"elapsed_time":332697,"interval":1,"segment":1,"source_type":4,"start_time":1759156058996},{"elapsed_time":333697,"interval":1,"segment":1,"source_type":4,"start_time":1759156059996},{"elapsed_time":334697,"interval":1,"segment":1,"source_type":4,"start_time":1759156060996},{"elapsed_time":335697,"interval":1,"segment":1,"source_type":4,"start_time":1759156061996},{"elapsed_time":336697,"interval":1,"segment":1,"source_type":4,"start_time":1759156062996},{"elapsed_time":337697,"interval":1,"segment":1,"source_type":4,"start_time":1759156063996},{"elapsed_time":338697,"interval":1,"segment":1,"source_type":4,"start_time":1759156064996},{"elapsed_time":339697,"interval":1,"segment":1,"source_type":4,"start_time":1759156065996},{"elapsed_time":340697,"interval":1,"segment":1,"source_type":4,"start_time":1759156066996},{"elapsed_time":341697,"interval":1,"segment":1,"source_type":4,"start_time":1759156067996},{"elapsed_time":342697,"interval":1,"segment":1,"source_type":4,"start_time":1759156068996},{"elapsed_time":343697,"interval":1,"segment":1,"source_type":4,"start_time":1759156069996},{"elapsed_time":344697,"interval":1,"segment":1,"source_type":4,"start_time":1759156070996},{"elapsed_time":345697,"interval":1,"segment":1,"source_type":4,"start_time":1759156071996},{"elapsed_time":346697,"interval":1,"segment":1,"source_type":4,"start_time":1759156072996},{"elapsed_time":347697,"interval":1,"segment":1,"source_type":4,"start_time":1759156073996},{"elapsed_time":348697,"interval":1,"segment":1,"source_type":4,"start_time":1759156074996},{"elapsed_time":349697,"interval":1,"segment":1,"source_type":4,"start_time":1759156075996},{"elapsed_time":350697,"interval":1,"segment":1,"source_type":4,"start_time":1759156076996},{"elapsed_time":351697,"interval":1,"segment":1,"source_type":4,"start_time":1759156077996},{"elapsed_time":352697,"interval":1,"segment":1,"source_type":4,"start_time":1759156078996},{"elapsed_time":353697,"interval":1,"segment":1,"source_type":4,"start_time":1759156079996},{"elapsed_time":354697,"interval":1,"segment":1,"source_type":4,"start_time":1759156080996},{"elapsed_time":355697,"interval":1,"segment":1,"source_type":4,"start_time":1759156081996},{"elapsed_time":356697,"interval":1,"segment":1,"source_type":4,"start_time":1759156082996},{"elapsed_time":357697,"interval":1,"segment":1,"source_type":4,"start_time":1759156083996},{"elapsed_time":358697,"interval":1,"segment":1,"source_type":4,"start_time":1759156084996},{"elapsed_time":359697,"interval":1,"segment":1,"source_type":4,"start_time":1759156085996},{"elapsed_time":360697,"interval":1,"segment":1,"source_type":4,"start_time":1759156086996},{"elapsed_time":361697,"interval":1,"segment":1,"source_type":4,"start_time":1759156087996},{"elapsed_time":362697,"interval":1,"segment":1,"source_type":4,"start_time":1759156088996},{"elapsed_time":363697,"interval":1,"segment":1,"source_type":4,"start_time":1759156089996},{"elapsed_time":364697,"interval":1,"segment":1,"source_type":4,"start_time":1759156090996},{"elapsed_time":365697,"interval":1,"segment":1,"source_type":4,"start_time":1759156091996},{"elapsed_time":366697,"interval":1,"segment":1,"source_type":4,"start_time":1759156092996},{"elapsed_time":367697,"interval":1,"segment":1,"source_type":4,"start_time":1759156093996},{"elapsed_time":368697,"interval":1,"segment":1,"source_type":4,"start_time":1759156094996},{"elapsed_time":369697,"interval":1,"segment":1,"source_type":4,"start_time":1759156095996},{"elapsed_time":370697,"interval":1,"segment":1,"source_type":4,"start_time":1759156096996},{"elapsed_time":371697,"interval":1,"segment":1,"source_type":4,"start_time":1759156097996},{"elapsed_time":372697,"interval":1,"segment":1,"source_type":4,"start_time":1759156098996},{"elapsed_time":373697,"interval":1,"segment":1,"source_type":4,"start_time":1759156099996},{"elapsed_time":374697,"interval":1,"segment":1,"source_type":4,"start_time":1759156100996},{"elapsed_time":375697,"interval":1,"segment":1,"source_type":4,"start_time":1759156101996},{"elapsed_time":376697,"interval":1,"segment":1,"source_type":4,"start_time":1759156102996},{"elapsed_time":377697,"interval":1,"segment":1,"source_type":4,"start_time":1759156103996},{"elapsed_time":378697,"interval":1,"segment":1,"source_type":4,"start_time":1759156104996},{"elapsed_time":379697,"interval":1,"segment":1,"source_type":4,"start_time":1759156105996},{"elapsed_time":380697,"interval":1,"segment":1,"source_type":4,"start_time":1759156106996},{"elapsed_time":381697,"interval":1,"segment":1,"source_type":4,"start_time":1759156107996},{"elapsed_time":382697,"interval":1,"segment":1,"source_type":4,"start_time":1759156108996},{"elapsed_time":383697,"interval":1,"segment":1,"source_type":4,"start_time":1759156109996},{"elapsed_time":384697,"interval":1,"segment":1,"source_type":4,"start_time":1759156110996},{"elapsed_time":385697,"interval":1,"segment":1,"source_type":4,"start_time":1759156111996},{"elapsed_time":386697,"interval":1,"segment":1,"source_type":4,"start_time":1759156112996},{"elapsed_time":387697,"interval":1,"segment":1,"source_type":4,"start_time":1759156113996},{"elapsed_time":388697,"interval":1,"segment":1,"source_type":4,"start_time":1759156114996},{"elapsed_time":389697,"interval":1,"segment":1,"source_type":4,"start_time":1759156115996},{"elapsed_time":390697,"interval":1,"segment":1,"source_type":4,"start_time":1759156116996},{"elapsed_time":391697,"interval":1,"segment":1,"source_type":4,"start_time":1759156117996},{"elapsed_time":392697,"interval":1,"segment":1,"source_type":4,"start_time":1759156118996},{"elapsed_time":393697,"interval":1,"segment":1,"source_type":4,"start_time":1759156119996},{"elapsed_time":394697,"interval":1,"segment":1,"source_type":4,"start_time":1759156120996},{"elapsed_time":395697,"interval":1,"segment":1,"source_type":4,"start_time":1759156121996},{"elapsed_time":396697,"interval":1,"segment":1,"source_type":4,"start_time":1759156122996},{"elapsed_time":397697,"interval":1,"segment":1,"source_type":4,"start_time":1759156123996},{"elapsed_time":398697,"interval":1,"segment":1,"source_type":4,"start_time":1759156124996},{"elapsed_time":399697,"interval":1,"segment":1,"source_type":4,"start_time":1759156125996},{"elapsed_time":400697,"interval":1,"segment":1,"source_type":4,"start_time":1759156126996},{"elapsed_time":401697,"interval":1,"segment":1,"source_type":4,"start_time":1759156127996},{"elapsed_time":402697,"interval":1,"segment":1,"source_type":4,"start_time":1759156128996},{"elapsed_time":403697,"interval":1,"segment":1,"source_type":4,"start_time":1759156129996},{"elapsed_time":404697,"interval":1,"segment":1,"source_type":4,"start_time":1759156130996},{"elapsed_time":405697,"interval":1,"segment":1,"source_type":4,"start_time":1759156131996},{"elapsed_time":406697,"interval":1,"segment":1,"source_type":4,"start_time":1759156132996},{"elapsed_time":407697,"interval":1,"segment":1,"source_type":4,"start_time":1759156133996},{"elapsed_time":408697,"interval":1,"segment":1,"source_type":4,"start_time":1759156134996},{"elapsed_time":409697,"interval":1,"segment":1,"source_type":4,"start_time":1759156135996},{"elapsed_time":410697,"interval":1,"segment":1,"source_type":4,"start_time":1759156136996},{"elapsed_time":411697,"interval":1,"segment":1,"source_type":4,"start_time":1759156137996},{"elapsed_time":412697,"interval":1,"segment":1,"source_type":4,"start_time":1759156138996},{"elapsed_time":413697,"interval":1,"segment":1,"source_type":4,"start_time":1759156139996},{"elapsed_time":414697,"interval":1,"segment":1,"source_type":4,"start_time":1759156140996},{"elapsed_time":415697,"interval":1,"segment":1,"source_type":4,"start_time":1759156141996},{"elapsed_time":416697,"interval":1,"segment":1,"source_type":4,"start_time":1759156142996},{"elapsed_time":417697,"interval":1,"segment":1,"source_type":4,"start_time":1759156143996},{"elapsed_time":418697,"interval":1,"segment":1,"source_type":4,"start_time":1759156144996},{"elapsed_time":419697,"interval":1,"segment":1,"source_type":4,"start_time":1759156145996},{"elapsed_time":420697,"interval":1,"segment":1,"source_type":4,"start_time":1759156146996},{"elapsed_time":421697,"interval":1,"segment":1,"source_type":4,"start_time":1759156147996},{"elapsed_time":422697,"interval":1,"segment":1,"source_type":4,"start_time":1759156148996},{"elapsed_time":423697,"interval":1,"segment":1,"source_type":4,"start_time":1759156149996},{"elapsed_time":424697,"interval":1,"segment":1,"source_type":4,"start_time":1759156150996},{"elapsed_time":425697,"interval":1,"segment":1,"source_type":4,"start_time":1759156151996},{"elapsed_time":426697,"interval":1,"segment":1,"source_type":4,"start_time":1759156152996},{"elapsed_time":427697,"interval":1,"segment":1,"source_type":4,"start_time":1759156153996},{"elapsed_time":428697,"interval":1,"segment":1,"source_type":4,"start_time":1759156154996},{"elapsed_time":429697,"interval":1,"segment":1,"source_type":4,"start_time":1759156155996},{"elapsed_time":430697,"interval":1,"segment":1,"source_type":4,"start_time":1759156156996},{"elapsed_time":431697,"interval":1,"segment":1,"source_type":4,"start_time":1759156157996},{"elapsed_time":432697,"interval":1,"segment":1,"source_type":4,"start_time":1759156158996},{"elapsed_time":433697,"interval":1,"segment":1,"source_type":4,"start_time":1759156159996},{"elapsed_time":434697,"interval":1,"segment":1,"source_type":4,"start_time":1759156160996},{"elapsed_time":435697,"interval":1,"segment":1,"source_type":4,"start_time":1759156161996},{"elapsed_time":436697,"interval":1,"segment":1,"source_type":4,"start_time":1759156162996},{"elapsed_time":437697,"interval":1,"segment":1,"source_type":4,"start_time":1759156163996},{"elapsed_time":438697,"interval":1,"segment":1,"source_type":4,"start_time":1759156164996},{"elapsed_time":439697,"interval":1,"segment":1,"source_type":4,"start_time":1759156165996},{"elapsed_time":440697,"interval":1,"segment":1,"source_type":4,"start_time":1759156166996},{"elapsed_time":441697,"interval":1,"segment":1,"source_type":4,"start_time":1759156167996},{"elapsed_time":442697,"interval":1,"segment":1,"source_type":4,"start_time":1759156168996},{"elapsed_time":443697,"interval":1,"segment":1,"source_type":4,"start_time":1759156169996},{"elapsed_time":444697,"interval":1,"segment":1,"source_type":4,"start_time":1759156170996},{"elapsed_time":445697,"interval":1,"segment":1,"source_type":4,"start_time":1759156171996},{"elapsed_time":446697,"interval":1,"segment":1,"source_type":4,"start_time":1759156172996},{"elapsed_time":447697,"interval":1,"segment":1,"source_type":4,"start_time":1759156173996},{"elapsed_time":448697,"interval":1,"segment":1,"source_type":4,"start_time":1759156174996},{"elapsed_time":449697,"interval":1,"segment":1,"source_type":4,"start_time":1759156175996},{"elapsed_time":450697,"interval":1,"segment":1,"source_type":4,"start_time":1759156176996},{"elapsed_time":451697,"interval":1,"segment":1,"source_type":4,"start_time":1759156177996},{"elapsed_time":452697,"interval":1,"segment":1,"source_type":4,"start_time":1759156178996},{"elapsed_time":453697,"interval":1,"segment":1,"source_type":4,"start_time":1759156179996},{"elapsed_time":454697,"interval":1,"segment":1,"source_type":4,"start_time":1759156180996},{"elapsed_time":455697,"interval":1,"segment":1,"source_type":4,"start_time":1759156181996},{"elapsed_time":456697,"interval":1,"segment":1,"source_type":4,"start_time":1759156182996},{"elapsed_time":457697,"interval":1,"segment":1,"source_type":4,"start_time":1759156183996},{"elapsed_time":458697,"interval":1,"segment":1,"source_type":4,"start_time":1759156184996},{"elapsed_time":459697,"interval":1,"segment":1,"source_type":4,"start_time":1759156185996},{"elapsed_time":460697,"interval":1,"segment":1,"source_type":4,"start_time":1759156186996},{"elapsed_time":461697,"interval":1,"segment":1,"source_type":4,"start_time":1759156187996},{"elapsed_time":462697,"interval":1,"segment":1,"source_type":4,"start_time":1759156188996},{"elapsed_time":463697,"interval":1,"segment":1,"source_type":4,"start_time":1759156189996},{"elapsed_time":464697,"interval":1,"segment":1,"source_type":4,"start_time":1759156190996},{"elapsed_time":465697,"interval":1,"segment":1,"source_type":4,"start_time":1759156191996},{"elapsed_time":466697,"interval":1,"segment":1,"source_type":4,"start_time":1759156192996},{"elapsed_time":467697,"interval":1,"segment":1,"source_type":4,"start_time":1759156193996},{"elapsed_time":468697,"interval":1,"segment":1,"source_type":4,"start_time":1759156194996},{"elapsed_time":469697,"interval":1,"segment":1,"source_type":4,"start_time":1759156195996},{"elapsed_time":470697,"interval":1,"segment":1,"source_type":4,"start_time":1759156196996},{"elapsed_time":471697,"interval":1,"segment":1,"source_type":4,"start_time":1759156197996},{"elapsed_time":473697,"interval":1,"segment":1,"source_type":4,"start_time":1759156199996},{"elapsed_time":474697,"interval":1,"segment":1,"source_type":4,"start_time":1759156200996},{"elapsed_time":475697,"interval":1,"segment":1,"source_type":4,"start_time":1759156201996},{"elapsed_time":476697,"interval":1,"segment":1,"source_type":4,"start_time":1759156202996},{"elapsed_time":477697,"interval":1,"segment":1,"source_type":4,"start_time":1759156203996},{"elapsed_time":478697,"interval":1,"segment":1,"source_type":4,"start_time":1759156204996},{"elapsed_time":479697,"interval":1,"segment":1,"source_type":4,"start_time":1759156205996},{"elapsed_time":480697,"interval":1,"segment":1,"source_type":4,"start_time":1759156206996},{"elapsed_time":481697,"interval":1,"segment":1,"source_type":4,"start_time":1759156207996},{"elapsed_time":482697,"interval":1,"segment":1,"source_type":4,"start_time":1759156208996},{"elapsed_time":483697,"interval":1,"segment":1,"source_type":4,"start_time":1759156209996},{"elapsed_time":484697,"interval":1,"segment":1,"source_type":4,"start_time":1759156210996},{"elapsed_time":485697,"interval":1,"segment":1,"source_type":4,"start_time":1759156211996},{"elapsed_time":486697,"interval":1,"segment":1,"source_type":4,"start_time":1759156212996},{"elapsed_time":487697,"interval":1,"segment":1,"source_type":4,"start_time":1759156213996},{"elapsed_time":488697,"interval":1,"segment":1,"source_type":4,"start_time":1759156214996},{"elapsed_time":489697,"interval":1,"segment":1,"source_type":4,"start_time":1759156215996},{"elapsed_time":490697,"interval":1,"segment":1,"source_type":4,"start_time":1759156216996},{"elapsed_time":491697,"interval":1,"segment":1,"source_type":4,"start_time":1759156217996},{"elapsed_time":492697,"interval":1,"segment":1,"source_type":4,"start_time":1759156218996},{"elapsed_time":493697,"interval":1,"segment":1,"source_type":4,"start_time":1759156219996},{"elapsed_time":494697,"interval":1,"segment":1,"source_type":4,"start_time":1759156220996},{"elapsed_time":496697,"interval":1,"segment":1,"source_type":4,"start_time":1759156222996},{"elapsed_time":497697,"interval":1,"segment":1,"source_type":4,"start_time":1759156223996},{"elapsed_time":498697,"interval":1,"segment":1,"source_type":4,"start_time":1759156224996},{"elapsed_time":499697,"interval":1,"segment":1,"source_type":4,"start_time":1759156225996},{"elapsed_time":500697,"interval":1,"segment":1,"source_type":4,"start_time":1759156226996},{"elapsed_time":501697,"interval":1,"segment":1,"source_type":4,"start_time":1759156227996},{"elapsed_time":502697,"interval":1,"segment":1,"source_type":4,"start_time":1759156228996},{"elapsed_time":503697,"interval":1,"segment":1,"source_type":4,"start_time":1759156229996},{"elapsed_time":504697,"interval":1,"segment":1,"source_type":4,"start_time":1759156230996},{"elapsed_time":505697,"interval":1,"segment":1,"source_type":4,"start_time":1759156231996},{"elapsed_time":506697,"interval":1,"segment":1,"source_type":4,"start_time":1759156232996},{"elapsed_time":507697,"interval":1,"segment":1,"source_type":4,"start_time":1759156233996},{"elapsed_time":508697,"interval":1,"segment":1,"source_type":4,"start_time":1759156234996},{"elapsed_time":509697,"interval":1,"segment":1,"source_type":4,"start_time":1759156235996},{"elapsed_time":510697,"interval":1,"segment":1,"source_type":4,"start_time":1759156236996},{"elapsed_time":511697,"interval":1,"segment":1,"source_type":4,"start_time":1759156237996},{"elapsed_time":512697,"interval":1,"segment":1,"source_type":4,"start_time":1759156238996},{"elapsed_time":513697,"interval":1,"segment":1,"source_type":4,"start_time":1759156239996},{"elapsed_time":514697,"interval":1,"segment":1,"source_type":4,"start_time":1759156240996},{"elapsed_time":515697,"interval":1,"segment":1,"source_type":4,"start_time":1759156241996},{"elapsed_time":516697,"interval":1,"segment":1,"source_type":4,"start_time":1759156242996},{"elapsed_time":28697,"interval":1,"segment":1,"source_type":4,"start_time":1759155754996},{"elapsed_time":538854,"interval":1,"segment":1,"source_type":4,"start_time":1759156265153},{"elapsed_time":539854,"interval":1,"segment":1,"source_type":4,"start_time":1759156266153},{"elapsed_time":540854,"interval":1,"segment":1,"source_type":4,"start_time":1759156267153},{"elapsed_time":541854,"interval":1,"segment":1,"source_type":4,"start_time":1759156268153},{"elapsed_time":542854,"interval":1,"segment":1,"source_type":4,"start_time":1759156269153},{"elapsed_time":543854,"interval":1,"segment":1,"source_type":4,"start_time":1759156270153},{"elapsed_time":544854,"interval":1,"segment":1,"source_type":4,"start_time":1759156271153},{"elapsed_time":545854,"interval":1,"segment":1,"source_type":4,"start_time":1759156272153},{"elapsed_time":546854,"interval":1,"segment":1,"source_type":4,"start_time":1759156273153},{"elapsed_time":547854,"interval":1,"segment":1,"source_type":4,"start_time":1759156274153},{"elapsed_time":548854,"interval":1,"segment":1,"source_type":4,"start_time":1759156275153},{"elapsed_time":549854,"interval":1,"segment":1,"source_type":4,"start_time":1759156276153},{"elapsed_time":550854,"interval":1,"segment":1,"source_type":4,"start_time":1759156277153},{"elapsed_time":551854,"interval":1,"segment":1,"source_type":4,"start_time":1759156278153},{"elapsed_time":552854,"interval":1,"segment":1,"source_type":4,"start_time":1759156279153},{"elapsed_time":553854,"interval":1,"segment":1,"source_type":4,"start_time":1759156280153},{"elapsed_time":554854,"interval":1,"segment":1,"source_type":4,"start_time":1759156281153},{"elapsed_time":555854,"interval":1,"segment":1,"source_type":4,"start_time":1759156282153},{"elapsed_time":556854,"interval":1,"segment":1,"source_type":4,"start_time":1759156283153},{"elapsed_time":557854,"interval":1,"segment":1,"source_type":4,"start_time":1759156284153},{"elapsed_time":558854,"interval":1,"segment":1,"source_type":4,"start_time":1759156285153},{"elapsed_time":559854,"interval":1,"segment":1,"source_type":4,"start_time":1759156286153},{"elapsed_time":560854,"interval":1,"segment":1,"source_type":4,"start_time":1759156287153},{"elapsed_time":561854,"interval":1,"segment":1,"source_type":4,"start_time":1759156288153},{"elapsed_time":562854,"interval":1,"segment":1,"source_type":4,"start_time":1759156289153},{"elapsed_time":563854,"interval":1,"segment":1,"source_type":4,"start_time":1759156290153},{"elapsed_time":564854,"interval":1,"segment":1,"source_type":4,"start_time":1759156291153},{"elapsed_time":565854,"interval":1,"segment":1,"source_type":4,"start_time":1759156292153},{"elapsed_time":566854,"interval":1,"segment":1,"source_type":4,"start_time":1759156293153},{"elapsed_time":567854,"interval":1,"segment":1,"source_type":4,"start_time":1759156294153},{"elapsed_time":568854,"interval":1,"segment":1,"source_type":4,"start_time":1759156295153},{"elapsed_time":569854,"interval":1,"segment":1,"source_type":4,"start_time":1759156296153},{"elapsed_time":570854,"interval":1,"segment":1,"source_type":4,"start_time":1759156297153},{"elapsed_time":571854,"interval":1,"segment":1,"source_type":4,"start_time":1759156298153},{"elapsed_time":572854,"interval":1,"segment":1,"source_type":4,"start_time":1759156299153},{"elapsed_time":573854,"interval":1,"segment":1,"source_type":4,"start_time":1759156300153},{"elapsed_time":574854,"interval":1,"segment":1,"source_type":4,"start_time":1759156301153},{"elapsed_time":575854,"interval":1,"segment":1,"source_type":4,"start_time":1759156302153},{"elapsed_time":576854,"interval":1,"segment":1,"source_type":4,"start_time":1759156303153},{"elapsed_time":577854,"interval":1,"segment":1,"source_type":4,"start_time":1759156304153},{"elapsed_time":578854,"interval":1,"segment":1,"source_type":4,"start_time":1759156305153},{"elapsed_time":579854,"interval":1,"segment":1,"source_type":4,"start_time":1759156306153},{"elapsed_time":580854,"interval":1,"segment":1,"source_type":4,"start_time":1759156307153},{"elapsed_time":581854,"interval":1,"segment":1,"source_type":4,"start_time":1759156308153},{"elapsed_time":582854,"interval":1,"segment":1,"source_type":4,"start_time":1759156309153},{"elapsed_time":583854,"interval":1,"segment":1,"source_type":4,"start_time":1759156310153},{"elapsed_time":584854,"interval":1,"segment":1,"source_type":4,"start_time":1759156311153},{"elapsed_time":585854,"interval":1,"segment":1,"source_type":4,"start_time":1759156312153},{"elapsed_time":586854,"interval":1,"segment":1,"source_type":4,"start_time":1759156313153},{"elapsed_time":587854,"interval":1,"segment":1,"source_type":4,"start_time":1759156314153},{"elapsed_time":588854,"interval":1,"segment":1,"source_type":4,"start_time":1759156315153},{"elapsed_time":589854,"interval":1,"segment":1,"source_type":4,"start_time":1759156316153},{"elapsed_time":590854,"interval":1,"segment":1,"source_type":4,"start_time":1759156317153},{"elapsed_time":591854,"interval":1,"segment":1,"source_type":4,"start_time":1759156318153},{"elapsed_time":592854,"interval":1,"segment":1,"source_type":4,"start_time":1759156319153},{"elapsed_time":593854,"interval":1,"segment":1,"source_type":4,"start_time":1759156320153},{"elapsed_time":594854,"interval":1,"segment":1,"source_type":4,"start_time":1759156321153},{"elapsed_time":595854,"interval":1,"segment":1,"source_type":4,"start_time":1759156322153},{"elapsed_time":596854,"interval":1,"segment":1,"source_type":4,"start_time":1759156323153},{"elapsed_time":597854,"interval":1,"segment":1,"source_type":4,"start_time":1759156324153},{"elapsed_time":598854,"interval":1,"segment":1,"source_type":4,"start_time":1759156325153},{"elapsed_time":599854,"interval":1,"segment":1,"source_type":4,"start_time":1759156326153},{"elapsed_time":600854,"interval":1,"segment":1,"source_type":4,"start_time":1759156327153},{"elapsed_time":601854,"interval":1,"segment":1,"source_type":4,"start_time":1759156328153},{"elapsed_time":602854,"interval":1,"segment":1,"source_type":4,"start_time":1759156329153},{"elapsed_time":603854,"interval":1,"segment":1,"source_type":4,"start_time":1759156330153},{"elapsed_time":604854,"interval":1,"segment":1,"source_type":4,"start_time":1759156331153},{"elapsed_time":605854,"interval":1,"segment":1,"source_type":4,"start_time":1759156332153},{"elapsed_time":606854,"interval":1,"segment":1,"source_type":4,"start_time":1759156333153},{"elapsed_time":607854,"interval":1,"segment":1,"source_type":4,"start_time":1759156334153},{"elapsed_time":608854,"interval":1,"segment":1,"source_type":4,"start_time":1759156335153},{"elapsed_time":609854,"interval":1,"segment":1,"source_type":4,"start_time":1759156336153},{"elapsed_time":610835,"interval":1,"segment":1,"source_type":4,"start_time":1759156337134},{"elapsed_time":611759,"interval":1,"segment":1,"source_type":4,"start_time":1759156338058},{"elapsed_time":612759,"interval":1,"segment":1,"source_type":4,"start_time":1759156339058},{"elapsed_time":613759,"interval":1,"segment":1,"source_type":4,"start_time":1759156340058},{"elapsed_time":614759,"interval":1,"segment":1,"source_type":4,"start_time":1759156341058},{"elapsed_time":615759,"interval":1,"segment":1,"source_type":4,"start_time":1759156342058},{"elapsed_time":616759,"interval":1,"segment":1,"source_type":4,"start_time":1759156343058},{"elapsed_time":617759,"interval":1,"segment":1,"source_type":4,"start_time":1759156344058},{"elapsed_time":618759,"interval":1,"segment":1,"source_type":4,"start_time":1759156345058},{"elapsed_time":619759,"interval":1,"segment":1,"source_type":4,"start_time":1759156346058},{"elapsed_time":620759,"interval":1,"segment":1,"source_type":4,"start_time":1759156347058},{"elapsed_time":621759,"interval":1,"segment":1,"source_type":4,"start_time":1759156348058},{"elapsed_time":622759,"interval":1,"segment":1,"source_type":4,"start_time":1759156349058},{"elapsed_time":623759,"interval":1,"segment":1,"source_type":4,"start_time":1759156350058},{"elapsed_time":624759,"interval":1,"segment":1,"source_type":4,"start_time":1759156351058},{"elapsed_time":625759,"interval":1,"segment":1,"source_type":4,"start_time":1759156352058},{"elapsed_time":626759,"interval":1,"segment":1,"source_type":4,"start_time":1759156353058},{"elapsed_time":627759,"interval":1,"segment":1,"source_type":4,"start_time":1759156354058},{"elapsed_time":628759,"interval":1,"segment":1,"source_type":4,"start_time":1759156355058},{"elapsed_time":629759,"interval":1,"segment":1,"source_type":4,"start_time":1759156356058},{"elapsed_time":630759,"interval":1,"segment":1,"source_type":4,"start_time":1759156357058},{"elapsed_time":631759,"interval":1,"segment":1,"source_type":4,"start_time":1759156358058},{"elapsed_time":632759,"interval":1,"segment":1,"source_type":4,"start_time":1759156359058},{"elapsed_time":633759,"interval":1,"segment":1,"source_type":4,"start_time":1759156360058},{"elapsed_time":634759,"interval":1,"segment":1,"source_type":4,"start_time":1759156361058},{"elapsed_time":635759,"interval":1,"segment":1,"source_type":4,"start_time":1759156362058},{"elapsed_time":636759,"interval":1,"segment":1,"source_type":4,"start_time":1759156363058},{"elapsed_time":637759,"interval":1,"segment":1,"source_type":4,"start_time":1759156364058},{"elapsed_time":641759,"interval":1,"segment":1,"source_type":4,"start_time":1759156368058},{"elapsed_time":642759,"interval":1,"segment":1,"source_type":4,"start_time":1759156369058},{"elapsed_time":643759,"interval":1,"segment":1,"source_type":4,"start_time":1759156370058},{"elapsed_time":644759,"interval":1,"segment":1,"source_type":4,"start_time":1759156371058},{"elapsed_time":645759,"interval":1,"segment":1,"source_type":4,"start_time":1759156372058},{"elapsed_time":646759,"interval":1,"segment":1,"source_type":4,"start_time":1759156373058},{"elapsed_time":647759,"interval":1,"segment":1,"source_type":4,"start_time":1759156374058},{"elapsed_time":648759,"interval":1,"segment":1,"source_type":4,"start_time":1759156375058},{"elapsed_time":649759,"interval":1,"segment":1,"source_type":4,"start_time":1759156376058},{"elapsed_time":651593,"interval":1,"segment":2,"source_type":4,"start_time":1759156408192},{"elapsed_time":652593,"interval":1,"segment":2,"source_type":4,"start_time":1759156409192},{"elapsed_time":653593,"interval":1,"segment":2,"source_type":4,"start_time":1759156410192},{"elapsed_time":654593,"interval":1,"segment":2,"source_type":4,"start_time":1759156411192},{"elapsed_time":655593,"interval":1,"segment":2,"source_type":4,"start_time":1759156412192},{"elapsed_time":656593,"interval":1,"segment":2,"source_type":4,"start_time":1759156413192},{"elapsed_time":657593,"interval":1,"segment":2,"source_type":4,"start_time":1759156414192},{"elapsed_time":658593,"interval":1,"segment":2,"source_type":4,"start_time":1759156415192},{"elapsed_time":659593,"interval":1,"segment":2,"source_type":4,"start_time":1759156416192},{"elapsed_time":660593,"interval":1,"segment":2,"source_type":4,"start_time":1759156417192},{"elapsed_time":661593,"interval":1,"segment":2,"source_type":4,"start_time":1759156418192},{"elapsed_time":662593,"interval":1,"segment":2,"source_type":4,"start_time":1759156419192},{"elapsed_time":663593,"interval":1,"segment":2,"source_type":4,"start_time":1759156420192},{"elapsed_time":664593,"interval":1,"segment":2,"source_type":4,"start_time":1759156421192},{"elapsed_time":665593,"interval":1,"segment":2,"source_type":4,"start_time":1759156422192},{"elapsed_time":666593,"interval":1,"segment":2,"source_type":4,"start_time":1759156423192},{"elapsed_time":667593,"interval":1,"segment":2,"source_type":4,"start_time":1759156424192},{"elapsed_time":668593,"interval":1,"segment":2,"source_type":4,"start_time":1759156425192},{"elapsed_time":669593,"interval":1,"segment":2,"source_type":4,"start_time":1759156426192},{"elapsed_time":670593,"interval":1,"segment":2,"source_type":4,"start_time":1759156427192},{"elapsed_time":671593,"interval":1,"segment":2,"source_type":4,"start_time":1759156428192},{"elapsed_time":672593,"interval":1,"segment":2,"source_type":4,"start_time":1759156429192},{"elapsed_time":673593,"interval":1,"segment":2,"source_type":4,"start_time":1759156430192},{"elapsed_time":674593,"interval":1,"segment":2,"source_type":4,"start_time":1759156431192},{"elapsed_time":675593,"interval":1,"segment":2,"source_type":4,"start_time":1759156432192},{"elapsed_time":676593,"interval":1,"segment":2,"source_type":4,"start_time":1759156433192},{"elapsed_time":677593,"interval":1,"segment":2,"source_type":4,"start_time":1759156434192},{"elapsed_time":678593,"interval":1,"segment":2,"source_type":4,"start_time":1759156435192},{"elapsed_time":679593,"interval":1,"segment":2,"source_type":4,"start_time":1759156436192},{"elapsed_time":680593,"interval":1,"segment":2,"source_type":4,"start_time":1759156437192},{"elapsed_time":681593,"interval":1,"segment":2,"source_type":4,"start_time":1759156438192},{"elapsed_time":682593,"interval":1,"segment":2,"source_type":4,"start_time":1759156439192},{"elapsed_time":683593,"interval":1,"segment":2,"source_type":4,"start_time":1759156440192},{"elapsed_time":684593,"interval":1,"segment":2,"source_type":4,"start_time":1759156441192},{"elapsed_time":685593,"interval":1,"segment":2,"source_type":4,"start_time":1759156442192},{"elapsed_time":686593,"interval":1,"segment":2,"source_type":4,"start_time":1759156443192},{"elapsed_time":687593,"interval":1,"segment":2,"source_type":4,"start_time":1759156444192},{"elapsed_time":688593,"interval":1,"segment":2,"source_type":4,"start_time":1759156445192},{"elapsed_time":689593,"interval":1,"segment":2,"source_type":4,"start_time":1759156446192},{"elapsed_time":690593,"interval":1,"segment":2,"source_type":4,"start_time":1759156447192},{"elapsed_time":691593,"interval":1,"segment":2,"source_type":4,"start_time":1759156448192},{"elapsed_time":692593,"interval":1,"segment":2,"source_type":4,"start_time":1759156449192},{"elapsed_time":693593,"interval":1,"segment":2,"source_type":4,"start_time":1759156450192},{"elapsed_time":694593,"interval":1,"segment":2,"source_type":4,"start_time":1759156451192},{"elapsed_time":695593,"interval":1,"segment":2,"source_type":4,"start_time":1759156452192},{"elapsed_time":696593,"interval":1,"segment":2,"source_type":4,"start_time":1759156453192},{"elapsed_time":698070,"interval":1,"segment":3,"source_type":4,"start_time":1759156463192},{"elapsed_time":699070,"interval":1,"segment":3,"source_type":4,"start_time":1759156464192},{"elapsed_time":700070,"interval":1,"segment":3,"source_type":4,"start_time":1759156465192},{"elapsed_time":701070,"interval":1,"segment":3,"source_type":4,"start_time":1759156466192},{"elapsed_time":702070,"interval":1,"segment":3,"source_type":4,"start_time":1759156467192},{"elapsed_time":703070,"interval":1,"segment":3,"source_type":4,"start_time":1759156468192},{"elapsed_time":704070,"interval":1,"segment":3,"source_type":4,"start_time":1759156469192},{"elapsed_time":705070,"interval":1,"segment":3,"source_type":4,"start_time":1759156470192},{"elapsed_time":706070,"interval":1,"segment":3,"source_type":4,"start_time":1759156471192},{"elapsed_time":707070,"interval":1,"segment":3,"source_type":4,"start_time":1759156472192},{"elapsed_time":708070,"interval":1,"segment":3,"source_type":4,"start_time":1759156473192},{"elapsed_time":709070,"interval":1,"segment":3,"source_type":4,"start_time":1759156474192},{"elapsed_time":710070,"interval":1,"segment":3,"source_type":4,"start_time":1759156475192},{"elapsed_time":711070,"interval":1,"segment":3,"source_type":4,"start_time":1759156476192},{"elapsed_time":712070,"interval":1,"segment":3,"source_type":4,"start_time":1759156477192},{"elapsed_time":713070,"interval":1,"segment":3,"source_type":4,"start_time":1759156478192},{"elapsed_time":714070,"interval":1,"segment":3,"source_type":4,"start_time":1759156479192},{"elapsed_time":715070,"interval":1,"segment":3,"source_type":4,"start_time":1759156480192},{"elapsed_time":716070,"interval":1,"segment":3,"source_type":4,"start_time":1759156481192},{"elapsed_time":717070,"interval":1,"segment":3,"source_type":4,"start_time":1759156482192},{"elapsed_time":718070,"interval":1,"segment":3,"source_type":4,"start_time":1759156483192}]